Workbook

Sheet Drivers
A1: ROCKET LAB USA (RKLB) — INTEGRATED MODEL: DRIVERS & ASSUMPTIONS
A2: As of June 3, 2026 | $M unless noted | Blue=input, Black=formula | Pre-profit growth name: EV/Rev + capacity multiples are the cleaner gauge
A4: SEGMENT REVENUE BUILD ($M)
A5: ($ in millions) | C5: FY2024A | D5: FY2025A | E5: FY2026E | F5: FY2027E | G5: FY2028E | H5: FY2029E | I5: FY2030E | J5: FY2031E
A6: Launch Services (Electron + Neutron) | C6: 125 | D6: 199 | E6: 260 | F6: 550 | G6: 1100 | H6: 1700 | I6: 2300 | J6: 2900
A7: Space Systems (incl. Mynaric) | C7: 311 | D7: 403 | E7: 610 | F7: 825 | G7: 1080 | H7: 1380 | I7: 1700 | J7: 2050
A8: Total revenue | C8: =SUM(C6:C7) | D8: =SUM(D6:D7) | E8: =SUM(E6:E7) | F8: =SUM(F6:F7) | G8: =SUM(G6:G7) | H8: =SUM(H6:H7) | I8: =SUM(I6:I7) | J8: =SUM(J6:J7)
A9: Total revenue growth % | C9: n/a | D9: =D8/C8-1 | E9: =E8/D8-1 | F9: =F8/E8-1 | G9: =G8/F8-1 | H9: =H8/G8-1 | I9: =I8/H8-1 | J9: =J8/I8-1
A11: CAPACITY & UNIT ECONOMICS
A12: ($ in millions) | C12: FY2024A | D12: FY2025A | E12: FY2026E | F12: FY2027E | G12: FY2028E | H12: FY2029E | I12: FY2030E | J12: FY2031E
A13: Electron + HASTE launches per year | C13: 16 | D13: 21 | E13: 22 | F13: 28 | G13: 30 | H13: 32 | I13: 32 | J13: 32
A14: Neutron launches per year | C14: 0 | D14: 0 | E14: 1 | F14: 5 | G14: 12 | H14: 16 | I14: 18 | J14: 20
A15: Neutron avg price per launch ($M) | C15: 0 | D15: 0 | E15: 50 | F15: 52 | G15: 53 | H15: 54 | I15: 55 | J15: 55
A17: MARGIN & FCF DRIVERS
A18: ($ in millions) | C18: FY2024A | D18: FY2025A | E18: FY2026E | F18: FY2027E | G18: FY2028E | H18: FY2029E | I18: FY2030E | J18: FY2031E
A19: Gross margin % | C19: 0.27 | D19: 0.3 | E19: 0.36 | F19: 0.4 | G19: 0.42 | H19: 0.45 | I19: 0.47 | J19: 0.48
A20: Operating margin % (EBIT) | C20: -0.44 | D20: -0.38 | E20: -0.2 | F20: -0.05 | G20: 0.05 | H20: 0.1 | I20: 0.13 | J20: 0.15
A21: D&A ($M) | C21: 30 | D21: 40 | E21: 55 | F21: 85 | G21: 120 | H21: 150 | I21: 175 | J21: 195
A22: Capex ($M) | C22: 80 | D22: 120 | E22: 180 | F22: 220 | G22: 200 | H22: 170 | I22: 150 | J22: 140
A23: Cash tax rate % | C23: 0 | D23: 0 | E23: 0 | F23: 0 | G23: 0.1 | H23: 0.15 | I23: 0.21 | J23: 0.21
A25: MARKET DATA & WACC INPUTS
A26: Current share price ($) | C26: 123.32
A27: Diluted shares (M) | C27: 608
A28: Total debt ($M) | C28: 38
A29: Cash & marketable securities ($M) | C29: 1480
A30: Risk-free rate % | C30: 0.043
A31: Equity risk premium % | C31: 0.05
A32: Beta | C32: 1.8
A33: Pre-tax cost of debt % | C33: 0.06
A34: Terminal growth rate % | C34: 0.035
A36: WACC (computed)
A37: Cost of equity | C37: =C30+C32*C31
A38: After-tax cost of debt | C38: =C33*(1-J23)
A39: Market value of equity ($M) | C39: =C26*C27
A40: Net cash (debt) ($M) | C40: =C29-C28
A41: Equity weight | C41: =C39/(C39+C28)
A42: Debt weight | C42: =C28/(C39+C28)
A43: WACC | C43: =C41*C37+C42*C38

Sheet Income Statement
A1: INCOME STATEMENT ($M)
A4: ($ in millions) | C4: FY2024A | D4: FY2025A | E4: FY2026E | F4: FY2027E | G4: FY2028E | H4: FY2029E | I4: FY2030E | J4: FY2031E
A5: Total revenue | C5: =Drivers!C8 | D5: =Drivers!D8 | E5: =Drivers!E8 | F5: =Drivers!F8 | G5: =Drivers!G8 | H5: =Drivers!H8 | I5: =Drivers!I8 | J5: =Drivers!J8
A6: Gross profit | C6: =C5*Drivers!C19 | D6: =D5*Drivers!D19 | E6: =E5*Drivers!E19 | F6: =F5*Drivers!F19 | G6: =G5*Drivers!G19 | H6: =H5*Drivers!H19 | I6: =I5*Drivers!I19 | J6: =J5*Drivers!J19
A7: Operating income (EBIT) | C7: =Drivers!C20*C5 | D7: =Drivers!D20*D5 | E7: =Drivers!E20*E5 | F7: =Drivers!F20*F5 | G7: =Drivers!G20*G5 | H7: =Drivers!H20*H5 | I7: =Drivers!I20*I5 | J7: =Drivers!J20*J5
A8: (+) D&A | C8: =Drivers!C21 | D8: =Drivers!D21 | E8: =Drivers!E21 | F8: =Drivers!F21 | G8: =Drivers!G21 | H8: =Drivers!H21 | I8: =Drivers!I21 | J8: =Drivers!J21
A9: EBITDA | C9: =C7+C8 | D9: =D7+D8 | E9: =E7+E8 | F9: =F7+F8 | G9: =G7+G8 | H9: =H7+H8 | I9: =I7+I8 | J9: =J7+J8
A10: Pre-tax income (~ EBIT, modest int.) | C10: =C7 | D10: =D7 | E10: =E7 | F10: =F7 | G10: =G7 | H10: =H7 | I10: =I7 | J10: =J7
A11: (-) Income taxes | C11: =C10*Drivers!C23 | D11: =D10*Drivers!D23 | E11: =E10*Drivers!E23 | F11: =F10*Drivers!F23 | G11: =G10*Drivers!G23 | H11: =H10*Drivers!H23 | I11: =I10*Drivers!I23 | J11: =J10*Drivers!J23
A12: Net income (GAAP) | C12: =C10-C11 | D12: =D10-D11 | E12: =E10-E11 | F12: =F10-F11 | G12: =G10-G11 | H12: =H10-H11 | I12: =I10-I11 | J12: =J10-J11
A13: Net margin % | C13: =C12/C5 | D13: =D12/D5 | E13: =E12/E5 | F13: =F12/F5 | G13: =G12/G5 | H13: =H12/H5 | I13: =I12/I5 | J13: =J12/J5

Sheet Balance Sheet
A1: BALANCE SHEET (simplified, $M)
A4: ($ in millions) | C4: FY2024A | D4: FY2025A | E4: FY2026E | F4: FY2027E | G4: FY2028E | H4: FY2029E | I4: FY2030E | J4: FY2031E
A5: Cash + marketable securities | C5: 425 | D5: 1090 | E5: 1480 | F5: =E5+'Cash Flow'!F11+F8 | G5: =F5+'Cash Flow'!G11+G8 | H5: =G5+'Cash Flow'!H11+H8 | I5: =H5+'Cash Flow'!I11+I8 | J5: =I5+'Cash Flow'!J11+J8
A6: Backlog (memo, $M) | C6: 1070 | D6: 1850 | E6: 2220
A7: Total debt (incl. converts) | C7: 360 | D7: 100 | E7: 38 | F7: =38 | G7: =38 | H7: =38 | I7: =38 | J7: =38
A8: Equity issuance (ATM, $M) | F8: 0 | G8: 200 | H8: 0 | I8: 0 | J8: 0

Sheet Cash Flow
A1: CASH FLOW & FCF ($M)
A4: ($ in millions) | C4: FY2024A | D4: FY2025A | E4: FY2026E | F4: FY2027E | G4: FY2028E | H4: FY2029E | I4: FY2030E | J4: FY2031E
A5: EBIT | C5: ='Income Statement'!C7 | D5: ='Income Statement'!D7 | E5: ='Income Statement'!E7 | F5: ='Income Statement'!F7 | G5: ='Income Statement'!G7 | H5: ='Income Statement'!H7 | I5: ='Income Statement'!I7 | J5: ='Income Statement'!J7
A6: (-) Cash taxes on EBIT | C6: =MAX(C5,0)*Drivers!C23 | D6: =MAX(D5,0)*Drivers!D23 | E6: =MAX(E5,0)*Drivers!E23 | F6: =MAX(F5,0)*Drivers!F23 | G6: =MAX(G5,0)*Drivers!G23 | H6: =MAX(H5,0)*Drivers!H23 | I6: =MAX(I5,0)*Drivers!I23 | J6: =MAX(J5,0)*Drivers!J23
A7: NOPAT | C7: =C5-C6 | D7: =D5-D6 | E7: =E5-E6 | F7: =F5-F6 | G7: =G5-G6 | H7: =H5-H6 | I7: =I5-I6 | J7: =J5-J6
A8: (+) D&A | C8: =Drivers!C21 | D8: =Drivers!D21 | E8: =Drivers!E21 | F8: =Drivers!F21 | G8: =Drivers!G21 | H8: =Drivers!H21 | I8: =Drivers!I21 | J8: =Drivers!J21
A9: (-) Capex | C9: =Drivers!C22 | D9: =Drivers!D22 | E9: =Drivers!E22 | F9: =Drivers!F22 | G9: =Drivers!G22 | H9: =Drivers!H22 | I9: =Drivers!I22 | J9: =Drivers!J22
A10: (-) Increase in NWC (assumed 0) | C10: =0 | D10: =0 | E10: =0 | F10: =0 | G10: =0 | H10: =0 | I10: =0 | J10: =0
A11: Unlevered free cash flow | C11: =C7+C8-C9-C10 | D11: =D7+D8-D9-D10 | E11: =E7+E8-E9-E10 | F11: =F7+F8-F9-F10 | G11: =G7+G8-G9-G10 | H11: =H7+H8-H9-H10 | I11: =I7+I8-I9-I10 | J11: =J7+J8-J9-J10
A14: Unlevered FCF margin % | C14: =C11/Drivers!C8 | D14: =D11/Drivers!D8 | E14: =E11/Drivers!E8 | F14: =F11/Drivers!F8 | G14: =G11/Drivers!G8 | H14: =H11/Drivers!H8 | I14: =I11/Drivers!I8 | J14: =J11/Drivers!J8

Sheet DCF
A1: DISCOUNTED CASH FLOW VALUATION (small-cap growth; wide bands)
A4: Projection year | B4: FY2027E | C4: FY2028E | D4: FY2029E | E4: FY2030E | F4: FY2031E
A5: Period (n) | B5: =1 | C5: =2 | D5: =3 | E5: =4 | F5: =5
A6: Unlevered FCF | B6: ='Cash Flow'!F11 | C6: ='Cash Flow'!G11 | D6: ='Cash Flow'!H11 | E6: ='Cash Flow'!I11 | F6: ='Cash Flow'!J11
A7: Discount factor @ WACC | B7: =1/(1+Drivers!C43)^B5 | C7: =1/(1+Drivers!C43)^C5 | D7: =1/(1+Drivers!C43)^D5 | E7: =1/(1+Drivers!C43)^E5 | F7: =1/(1+Drivers!C43)^F5
A8: PV of unlevered FCF | B8: =B6*B7 | C8: =C6*C7 | D8: =D6*D7 | E8: =E6*E7 | F8: =F6*F7
A10: Sum of PV of explicit FCF (FY27-31) | C10: =SUM(B8:F8)
A11: Terminal-year FCF (FY2031) | C11: =F6
A12: Terminal value (Gordon) | C12: =F6*(1+Drivers!C34)/(Drivers!C43-Drivers!C34)
A13: PV of terminal value | C13: =C12*F7
A14: Enterprise value | C14: =C10+C13
A15: (+) Net cash | C15: =Drivers!C29-Drivers!C28
A16: Equity value | C16: =C14+C15
A17: Diluted shares (M) | C17: =Drivers!C27
A18: Implied value per share ($) | C18: =C16/C17
A19: Current share price ($) | C19: =Drivers!C26
A20: Upside / (downside) to current | C20: =C18/C19-1
A21: TV as % of enterprise value | C21: =C13/C14
A22: SENSITIVITY — Implied $/share: WACC (down) x Terminal growth (across)
B23: Terminal g → | C23: 0.025 | D23: 0.03 | E23: 0.035 | F23: 0.04 | G23: 0.045
A24: WACC ↓ | B24: 0.11 | C24: =(($B$6/(1+$B$24)^1+$C$6/(1+$B$24)^2+$D$6/(1+$B$24)^3+$E$6/(1+$B$24)^4+$F$6/(1+$B$24)^5)+(($F$6*(1+C$23)/($B$24-C$23))/(1+$B$24)^5)+Drivers!$C$29-Drivers!$C$28)/Drivers!$C$27 | D24: =(($B$6/(1+$B$24)^1+$C$6/(1+$B$24)^2+$D$6/(1+$B$24)^3+$E$6/(1+$B$24)^4+$F$6/(1+$B$24)^5)+(($F$6*(1+D$23)/($B$24-D$23))/(1+$B$24)^5)+Drivers!$C$29-Drivers!$C$28)/Drivers!$C$27 | E24: =(($B$6/(1+$B$24)^1+$C$6/(1+$B$24)^2+$D$6/(1+$B$24)^3+$E$6/(1+$B$24)^4+$F$6/(1+$B$24)^5)+(($F$6*(1+E$23)/($B$24-E$23))/(1+$B$24)^5)+Drivers!$C$29-Drivers!$C$28)/Drivers!$C$27 | F24: =(($B$6/(1+$B$24)^1+$C$6/(1+$B$24)^2+$D$6/(1+$B$24)^3+$E$6/(1+$B$24)^4+$F$6/(1+$B$24)^5)+(($F$6*(1+F$23)/($B$24-F$23))/(1+$B$24)^5)+Drivers!$C$29-Drivers!$C$28)/Drivers!$C$27 | G24: =(($B$6/(1+$B$24)^1+$C$6/(1+$B$24)^2+$D$6/(1+$B$24)^3+$E$6/(1+$B$24)^4+$F$6/(1+$B$24)^5)+(($F$6*(1+G$23)/($B$24-G$23))/(1+$B$24)^5)+Drivers!$C$29-Drivers!$C$28)/Drivers!$C$27
B25: 0.12 | C25: =(($B$6/(1+$B$25)^1+$C$6/(1+$B$25)^2+$D$6/(1+$B$25)^3+$E$6/(1+$B$25)^4+$F$6/(1+$B$25)^5)+(($F$6*(1+C$23)/($B$25-C$23))/(1+$B$25)^5)+Drivers!$C$29-Drivers!$C$28)/Drivers!$C$27 | D25: =(($B$6/(1+$B$25)^1+$C$6/(1+$B$25)^2+$D$6/(1+$B$25)^3+$E$6/(1+$B$25)^4+$F$6/(1+$B$25)^5)+(($F$6*(1+D$23)/($B$25-D$23))/(1+$B$25)^5)+Drivers!$C$29-Drivers!$C$28)/Drivers!$C$27 | E25: =(($B$6/(1+$B$25)^1+$C$6/(1+$B$25)^2+$D$6/(1+$B$25)^3+$E$6/(1+$B$25)^4+$F$6/(1+$B$25)^5)+(($F$6*(1+E$23)/($B$25-E$23))/(1+$B$25)^5)+Drivers!$C$29-Drivers!$C$28)/Drivers!$C$27 | F25: =(($B$6/(1+$B$25)^1+$C$6/(1+$B$25)^2+$D$6/(1+$B$25)^3+$E$6/(1+$B$25)^4+$F$6/(1+$B$25)^5)+(($F$6*(1+F$23)/($B$25-F$23))/(1+$B$25)^5)+Drivers!$C$29-Drivers!$C$28)/Drivers!$C$27 | G25: =(($B$6/(1+$B$25)^1+$C$6/(1+$B$25)^2+$D$6/(1+$B$25)^3+$E$6/(1+$B$25)^4+$F$6/(1+$B$25)^5)+(($F$6*(1+G$23)/($B$25-G$23))/(1+$B$25)^5)+Drivers!$C$29-Drivers!$C$28)/Drivers!$C$27
B26: 0.13 | C26: =(($B$6/(1+$B$26)^1+$C$6/(1+$B$26)^2+$D$6/(1+$B$26)^3+$E$6/(1+$B$26)^4+$F$6/(1+$B$26)^5)+(($F$6*(1+C$23)/($B$26-C$23))/(1+$B$26)^5)+Drivers!$C$29-Drivers!$C$28)/Drivers!$C$27 | D26: =(($B$6/(1+$B$26)^1+$C$6/(1+$B$26)^2+$D$6/(1+$B$26)^3+$E$6/(1+$B$26)^4+$F$6/(1+$B$26)^5)+(($F$6*(1+D$23)/($B$26-D$23))/(1+$B$26)^5)+Drivers!$C$29-Drivers!$C$28)/Drivers!$C$27 | E26: =(($B$6/(1+$B$26)^1+$C$6/(1+$B$26)^2+$D$6/(1+$B$26)^3+$E$6/(1+$B$26)^4+$F$6/(1+$B$26)^5)+(($F$6*(1+E$23)/($B$26-E$23))/(1+$B$26)^5)+Drivers!$C$29-Drivers!$C$28)/Drivers!$C$27 | F26: =(($B$6/(1+$B$26)^1+$C$6/(1+$B$26)^2+$D$6/(1+$B$26)^3+$E$6/(1+$B$26)^4+$F$6/(1+$B$26)^5)+(($F$6*(1+F$23)/($B$26-F$23))/(1+$B$26)^5)+Drivers!$C$29-Drivers!$C$28)/Drivers!$C$27 | G26: =(($B$6/(1+$B$26)^1+$C$6/(1+$B$26)^2+$D$6/(1+$B$26)^3+$E$6/(1+$B$26)^4+$F$6/(1+$B$26)^5)+(($F$6*(1+G$23)/($B$26-G$23))/(1+$B$26)^5)+Drivers!$C$29-Drivers!$C$28)/Drivers!$C$27
B27: 0.14 | C27: =(($B$6/(1+$B$27)^1+$C$6/(1+$B$27)^2+$D$6/(1+$B$27)^3+$E$6/(1+$B$27)^4+$F$6/(1+$B$27)^5)+(($F$6*(1+C$23)/($B$27-C$23))/(1+$B$27)^5)+Drivers!$C$29-Drivers!$C$28)/Drivers!$C$27 | D27: =(($B$6/(1+$B$27)^1+$C$6/(1+$B$27)^2+$D$6/(1+$B$27)^3+$E$6/(1+$B$27)^4+$F$6/(1+$B$27)^5)+(($F$6*(1+D$23)/($B$27-D$23))/(1+$B$27)^5)+Drivers!$C$29-Drivers!$C$28)/Drivers!$C$27 | E27: =(($B$6/(1+$B$27)^1+$C$6/(1+$B$27)^2+$D$6/(1+$B$27)^3+$E$6/(1+$B$27)^4+$F$6/(1+$B$27)^5)+(($F$6*(1+E$23)/($B$27-E$23))/(1+$B$27)^5)+Drivers!$C$29-Drivers!$C$28)/Drivers!$C$27 | F27: =(($B$6/(1+$B$27)^1+$C$6/(1+$B$27)^2+$D$6/(1+$B$27)^3+$E$6/(1+$B$27)^4+$F$6/(1+$B$27)^5)+(($F$6*(1+F$23)/($B$27-F$23))/(1+$B$27)^5)+Drivers!$C$29-Drivers!$C$28)/Drivers!$C$27 | G27: =(($B$6/(1+$B$27)^1+$C$6/(1+$B$27)^2+$D$6/(1+$B$27)^3+$E$6/(1+$B$27)^4+$F$6/(1+$B$27)^5)+(($F$6*(1+G$23)/($B$27-G$23))/(1+$B$27)^5)+Drivers!$C$29-Drivers!$C$28)/Drivers!$C$27
B28: 0.15 | C28: =(($B$6/(1+$B$28)^1+$C$6/(1+$B$28)^2+$D$6/(1+$B$28)^3+$E$6/(1+$B$28)^4+$F$6/(1+$B$28)^5)+(($F$6*(1+C$23)/($B$28-C$23))/(1+$B$28)^5)+Drivers!$C$29-Drivers!$C$28)/Drivers!$C$27 | D28: =(($B$6/(1+$B$28)^1+$C$6/(1+$B$28)^2+$D$6/(1+$B$28)^3+$E$6/(1+$B$28)^4+$F$6/(1+$B$28)^5)+(($F$6*(1+D$23)/($B$28-D$23))/(1+$B$28)^5)+Drivers!$C$29-Drivers!$C$28)/Drivers!$C$27 | E28: =(($B$6/(1+$B$28)^1+$C$6/(1+$B$28)^2+$D$6/(1+$B$28)^3+$E$6/(1+$B$28)^4+$F$6/(1+$B$28)^5)+(($F$6*(1+E$23)/($B$28-E$23))/(1+$B$28)^5)+Drivers!$C$29-Drivers!$C$28)/Drivers!$C$27 | F28: =(($B$6/(1+$B$28)^1+$C$6/(1+$B$28)^2+$D$6/(1+$B$28)^3+$E$6/(1+$B$28)^4+$F$6/(1+$B$28)^5)+(($F$6*(1+F$23)/($B$28-F$23))/(1+$B$28)^5)+Drivers!$C$29-Drivers!$C$28)/Drivers!$C$27 | G28: =(($B$6/(1+$B$28)^1+$C$6/(1+$B$28)^2+$D$6/(1+$B$28)^3+$E$6/(1+$B$28)^4+$F$6/(1+$B$28)^5)+(($F$6*(1+G$23)/($B$28-G$23))/(1+$B$28)^5)+Drivers!$C$29-Drivers!$C$28)/Drivers!$C$27
A30: Center cell (WACC 13.0% / g 3.5%) = base case. Wider WACC band reflects small-cap + pre-profit + execution risk.

Sheet Notes
A1: RKLB MODEL — METHODOLOGY & CAVEATS
A3: Methodology — small-cap-growth adaptation
A4: Standard DCF mechanics, but with wider WACC range (11-15%) and a Neutron-conditional FCF profile.
A5: Revenue split: Launch Services (Electron + Neutron) + Space Systems (incl. Mynaric optical comms).
A6: Pre-profit through FY27; first profitable year FY28 in base case (Neutron 12 launches @ ~$53M).
A7: Wide sensitivity bands reflect single-product (Neutron) execution risk + pre-profit base.
A9: Base case stance
A10: Revenue: $602M (FY25 actual) -> $870M (FY26) -> $1.65B (FY27 first Neutron commercial yr) -> $4.95B (FY31)
A11: Op margin: -38% (FY25) -> -20% (FY26) -> -5% (FY27) -> +5% (FY28) -> +15% (FY31)
A12: Neutron: Q4 2026 first flight (expendable), 5 in FY27, 18-20/yr at mature cadence
A13: WACC 13.0% (beta 1.8, near-100% equity weight); terminal g 3.5% (space secular)
A15: Data sources & caveats
... A21: Research / decision-framing only — NOT investment advice.
