Workbook

Sheet Inputs
A1: SPACE / SAT-COMMS — COMPARABLE COMPANY ANALYSIS (RKLB target)
A2: Rocket Lab USA (RKLB) • AST SpaceMobile (ASTS) • Planet Labs (PL) • Iridium (IRDM) • Redwire (RDW) • Lockheed Martin (LMT) • SpaceX (private) (—)
A3: As of June 3, 2026 | $M except ratios | Pre-profit cohort: EV/Revenue is the cleaner gauge | LMT = old-space anchor; SpaceX = private benchmark (memo)
A5: RAW INPUTS — cell comments cite source / assumption
A6: Company | B6: Ticker | C6: Mkt Cap | D6: Net Debt | E6: Revenue (TTM) | F6: Rev Growth % | G6: Gross Margin % | H6: EBITDA (TTM) | I6: Net Income (TTM) | J6: Role | K6: Notes
A7: Rocket Lab USA | B7: RKLB | C7: 74974 | D7: -1442 | E7: 679 | F7: 0.635 | G7: 0.382 | H7: -50 | I7: -220 | J7: TARGET
A8: AST SpaceMobile | B8: ASTS | C8: 35330 | D8: -500 | E8: 85 | F8: 20 | G8: 0.69 | H8: -200 | I8: -600 | J8: PUBLIC PEER
A9: Planet Labs | B9: PL | C9: 15400 | D9: -178 | E9: 308 | F9: 0.41 | G9: 0.56 | H9: 15.5 | I9: -247 | J9: PUBLIC PEER
A10: Iridium | B10: IRDM | C10: 5250 | D10: 1700 | E10: 887 | F10: 0.02 | G10: 0.74 | H10: 474 | I10: 105 | J10: PUBLIC PEER
A11: Redwire | B11: RDW | C11: 4070 | D11: -55 | E11: 432 | F11: 0.579 | G11: 0.266 | H11: -40 | I11: -227 | J11: PUBLIC PEER
A12: Lockheed Martin | B12: LMT | C12: 121000 | D12: 18800 | E12: 75100 | F12: 0 | G12: 0.11 | H12: 10000 | I12: 5500 | J12: OLD-SPACE ANCHOR
A13: SpaceX (private) | B13: — | C13: 1750000 | D13: 0 | E13: 18674 | F13: 0.43 | G13: 0.4 | H13: 6584 | I13: -2589 | J13: PRIVATE (memo)

Sheet Valuation
A1: VALUATION — EV/REVENUE THE CLEANER GAUGE FOR THIS COHORT
A2: EV = Mkt Cap + Net Debt (negative net debt = net cash). EV/EBITDA shown but mostly NM (negative or NM).
A6: Company | B6: Mkt Cap | C6: EV | D6: EV / Rev | E6: EV / EBITDA | F6: P/E (TTM) | G6: Comment
A7: Rocket Lab USA | B7: =Inputs!C7 | C7: =Inputs!C7+Inputs!D7 | D7: =(Inputs!C7+Inputs!D7)/Inputs!E7 | E7: =IF(Inputs!H7>0,(Inputs!C7+Inputs!D7)/Inputs!H7,"NM") | F7: =IF(Inputs!I7>0,Inputs!C7/Inputs!I7,"NM") | G7: Target. ~110x EV/Rev — top of public cohort ex-ASTS. Bifurcated story; pre-profit but scaling fast.
A8: AST SpaceMobile | B8: =Inputs!C8 | C8: =Inputs!C8+Inputs!D8 | D8: =(Inputs!C8+Inputs!D8)/Inputs!E8 | E8: =IF(Inputs!H8>0,(Inputs!C8+Inputs!D8)/Inputs!H8,"NM") | F8: =IF(Inputs!I8>0,Inputs!C8/Inputs!I8,"NM") | G8: ~410x EV/Rev — pure pre-revenue story-stock; not useful as a multiple anchor.
A9: Planet Labs | B9: =Inputs!C9 | C9: =Inputs!C9+Inputs!D9 | D9: =(Inputs!C9+Inputs!D9)/Inputs!E9 | E9: =IF(Inputs!H9>0,(Inputs!C9+Inputs!D9)/Inputs!H9,"NM") | F9: =IF(Inputs!I9>0,Inputs!C9/Inputs!I9,"NM") | G9: ~49x EV/Rev — subscription Earth-obs; NDR 116%; first adj EBITDA+ year.
A10: Iridium | B10: =Inputs!C10 | C10: =Inputs!C10+Inputs!D10 | D10: =(Inputs!C10+Inputs!D10)/Inputs!E10 | E10: =IF(Inputs!H10>0,(Inputs!C10+Inputs!D10)/Inputs!H10,"NM") | F10: =IF(Inputs!I10>0,Inputs!C10/Inputs!I10,"NM") | G10: ~7-8x EV/Rev — the FCF/maturity-state anchor; profitable; cash returns.
A11: Redwire | B11: =Inputs!C11 | C11: =Inputs!C11+Inputs!D11 | D11: =(Inputs!C11+Inputs!D11)/Inputs!E11 | E11: =IF(Inputs!H11>0,(Inputs!C11+Inputs!D11)/Inputs!H11,"NM") | F11: =IF(Inputs!I11>0,Inputs!C11/Inputs!I11,"NM") | G11: ~9x EV/Rev — closest space-infra growth comp; pre-profit; Edge Autonomy reshape.
A12: Lockheed Martin | B12: =Inputs!C12 | C12: =Inputs!C12+Inputs!D12 | D12: =(Inputs!C12+Inputs!D12)/Inputs!E12 | E12: =IF(Inputs!H12>0,(Inputs!C12+Inputs!D12)/Inputs!H12,"NM") | F12: =IF(Inputs!I12>0,Inputs!C12/Inputs!I12,"NM") | G12: ~1.85x EV/Rev — old-space anchor; mature defense multiple; Space segment ~$13B/yr at ~10% margin.
A13: SpaceX (private) | B13: =Inputs!C13 | C13: =Inputs!C13+Inputs!D13 | D13: =(Inputs!C13+Inputs!D13)/Inputs!E13 | E13: =IF(Inputs!H13>0,(Inputs!C13+Inputs!D13)/Inputs!H13,"NM") | F13: =IF(Inputs!I13>0,Inputs!C13/Inputs!I13,"NM") | G13: ~95x EV/Rev at $1.75T IPO target (~$18.7B FY25 rev). Private mark. Set the upper bound of public valuation.

Sheet Capacity
A1: OPERATING CAPACITY — Launches/yr · Backlog · Pure-play status
A3: Company | B3: Launches / yr | C3: Backlog ($) | D3: Pure-play
A4: Rocket Lab | B4: 21 (FY25)→ Neutron Q4 26 | C4: $2.22B (+108% YoY) | D4: Yes — bifurcated
A5: AST SpaceMobile | B5: Sat ops (45 BlueBird YE26) | C5: $1.2B+ commercial pipeline | D5: Yes — direct-to-cell
A6: Planet Labs | B6: Subscription (no launches) | C6: $900M+ (+79% YoY) | D6: Yes — EO subscription
A7: Iridium | B7: Sat ops only | C7: n/a (subscription) | D7: Yes — satcom
A8: Redwire | B8: Component supplier | C8: $498M (+71% YoY) | D8: Yes — space infra
A9: Lockheed Martin | B9: 10+ heavy launches (Atlas/Vulcan-adj) | C9: $186.4B company-wide | D9: No — Space is 17% of revenue
A10: SpaceX | B10: ~140 Falcon 9 + Starship | C10: n/a (private) | D10: Yes — launch + Starlink

Sheet Notes
A1: NOTES — small-cap-growth peer framing
A3: Peer framing
A4: Pre-profit cohort: EV/Revenue is the cleaner multiple (most peers have negative or NM EBITDA).
A5: Public peers: ASTS (pre-rev option), PL (subscription EO, first adj EBITDA+), IRDM (mature satcom, cash returns), RDW (closest growth comp).
A6: LMT included as 'old-space' anchor — Space segment ~$13B/yr at ~10% op margin; sets the mature-state proxy.
A7: SpaceX as private memo — recently filed S-1 (April 2026, IPO target $1.75-2T per Bloomberg); FY25 revenue $18.7B.
A9: Key observations
A10: RKLB EV/Rev ~110x vs PL 49x, RDW 9x, IRDM 7.5x, ASTS 410x — RKLB sits in the upper-growth zone.
A11: Analyst consensus PT $103.91 (S&P Global poll of 18 analysts) is ~16% BELOW spot $123.32 — Street view skeptical.
A12: RKLB has rocketed ~5-6x from $20-30 levels in early 2025; current price embeds heroic terminal assumptions.
A13: Companion: RKLB-Model.xlsx (DCF base $9.35 vs $123 market — 'too conservative' or 'right'? You decide).
A15: Data sources & caveats
... A20: MCP terminals NOT configured. Research only, NOT investment advice.
