Workbook

Sheet Notes
A1: Model notes & assumptions
A3: STRUCTURE
A4: • 12-year horizon (FY24A FY25A FY26E-FY35E) — required for pre-profit
A5: quantum company where most enterprise value is terminal.
A6: • Two valuation frameworks side-by-side:
A7: 1. TRADITIONAL DCF: WACC-discounted FCF + Gordon terminal.
A8: Honest intrinsic value. Expected to be FAR below current price
A9: (the QC sector trades on optionality, not DCF).
A10: 2. REVERSE-ENGINEERED IPO VALUATION: holding current $68 price constant,
A11: solve for required FY35E revenue + implied % of McKinsey QC TAM.
A12: This is the right tool for pre-profit / pre-FTQC optionality names.
A14: REVENUE BUILD — 4 STREAMS
... A50: • If management raises post-IPO guidance, refresh segment growth tracks.

Sheet Sensitivity
A1: Sensitivity: Implied price per share — Traditional DCF (WACC x terminal g)
B3: WACC → | C3: =Drivers!C27+-0.02 | D3: =Drivers!C27+-0.01 | E3: =Drivers!C27+0 | F3: =Drivers!C27+0.01 | G3: =Drivers!C27+0.02
B4: =Drivers!C28+-0.015 | C4: =DCF!C19 * ((1+(Drivers!C28+-0.015))/((Drivers!C27+-0.02)-(Drivers!C28+-0.015))) / ((1+Drivers!C28)/(Drivers!C27-Drivers!C28)) | D4: =DCF!C19 * ((1+(Drivers!C28+-0.015))/((Drivers!C27+-0.01)-(Drivers!C28+-0.015))) / ((1+Drivers!C28)/(Drivers!C27-Drivers!C28)) | E4: =DCF!C19 * ((1+(Drivers!C28+-0.015))/((Drivers!C27+0)-(Drivers!C28+-0.015))) / ((1+Drivers!C28)/(Drivers!C27-Drivers!C28)) | F4: =DCF!C19 * ((1+(Drivers!C28+-0.015))/((Drivers!C27+0.01)-(Drivers!C28+-0.015))) / ((1+Drivers!C28)/(Drivers!C27-Drivers!C28)) | G4: =DCF!C19 * ((1+(Drivers!C28+-0.015))/((Drivers!C27+0.02)-(Drivers!C28+-0.015))) / ((1+Drivers!C28)/(Drivers!C27-Drivers!C28))
B5: =Drivers!C28+-0.005 | C5: =DCF!C19 * ((1+(Drivers!C28+-0.005))/((Drivers!C27+-0.02)-(Drivers!C28+-0.005))) / ((1+Drivers!C28)/(Drivers!C27-Drivers!C28)) | D5: =DCF!C19 * ((1+(Drivers!C28+-0.005))/((Drivers!C27+-0.01)-(Drivers!C28+-0.005))) / ((1+Drivers!C28)/(Drivers!C27-Drivers!C28)) | E5: =DCF!C19 * ((1+(Drivers!C28+-0.005))/((Drivers!C27+0)-(Drivers!C28+-0.005))) / ((1+Drivers!C28)/(Drivers!C27-Drivers!C28)) | F5: =DCF!C19 * ((1+(Drivers!C28+-0.005))/((Drivers!C27+0.01)-(Drivers!C28+-0.005))) / ((1+Drivers!C28)/(Drivers!C27-Drivers!C28)) | G5: =DCF!C19 * ((1+(Drivers!C28+-0.005))/((Drivers!C27+0.02)-(Drivers!C28+-0.005))) / ((1+Drivers!C28)/(Drivers!C27-Drivers!C28))
B6: =Drivers!C28+0 | C6: =DCF!C19 * ((1+(Drivers!C28+0))/((Drivers!C27+-0.02)-(Drivers!C28+0))) / ((1+Drivers!C28)/(Drivers!C27-Drivers!C28)) | D6: =DCF!C19 * ((1+(Drivers!C28+0))/((Drivers!C27+-0.01)-(Drivers!C28+0))) / ((1+Drivers!C28)/(Drivers!C27-Drivers!C28)) | E6: =DCF!C19 * ((1+(Drivers!C28+0))/((Drivers!C27+0)-(Drivers!C28+0))) / ((1+Drivers!C28)/(Drivers!C27-Drivers!C28)) | F6: =DCF!C19 * ((1+(Drivers!C28+0))/((Drivers!C27+0.01)-(Drivers!C28+0))) / ((1+Drivers!C28)/(Drivers!C27-Drivers!C28)) | G6: =DCF!C19 * ((1+(Drivers!C28+0))/((Drivers!C27+0.02)-(Drivers!C28+0))) / ((1+Drivers!C28)/(Drivers!C27-Drivers!C28))
B7: =Drivers!C28+0.005 | C7: =DCF!C19 * ((1+(Drivers!C28+0.005))/((Drivers!C27+-0.02)-(Drivers!C28+0.005))) / ((1+Drivers!C28)/(Drivers!C27-Drivers!C28)) | D7: =DCF!C19 * ((1+(Drivers!C28+0.005))/((Drivers!C27+-0.01)-(Drivers!C28+0.005))) / ((1+Drivers!C28)/(Drivers!C27-Drivers!C28)) | E7: =DCF!C19 * ((1+(Drivers!C28+0.005))/((Drivers!C27+0)-(Drivers!C28+0.005))) / ((1+Drivers!C28)/(Drivers!C27-Drivers!C28)) | F7: =DCF!C19 * ((1+(Drivers!C28+0.005))/((Drivers!C27+0.01)-(Drivers!C28+0.005))) / ((1+Drivers!C28)/(Drivers!C27-Drivers!C28)) | G7: =DCF!C19 * ((1+(Drivers!C28+0.005))/((Drivers!C27+0.02)-(Drivers!C28+0.005))) / ((1+Drivers!C28)/(Drivers!C27-Drivers!C28))
B8: =Drivers!C28+0.015 | C8: =DCF!C19 * ((1+(Drivers!C28+0.015))/((Drivers!C27+-0.02)-(Drivers!C28+0.015))) / ((1+Drivers!C28)/(Drivers!C27-Drivers!C28)) | D8: =DCF!C19 * ((1+(Drivers!C28+0.015))/((Drivers!C27+-0.01)-(Drivers!C28+0.015))) / ((1+Drivers!C28)/(Drivers!C27-Drivers!C28)) | E8: =DCF!C19 * ((1+(Drivers!C28+0.015))/((Drivers!C27+0)-(Drivers!C28+0.015))) / ((1+Drivers!C28)/(Drivers!C27-Drivers!C28)) | F8: =DCF!C19 * ((1+(Drivers!C28+0.015))/((Drivers!C27+0.01)-(Drivers!C28+0.015))) / ((1+Drivers!C28)/(Drivers!C27-Drivers!C28)) | G8: =DCF!C19 * ((1+(Drivers!C28+0.015))/((Drivers!C27+0.02)-(Drivers!C28+0.015))) / ((1+Drivers!C28)/(Drivers!C27-Drivers!C28))
A11: Current trading price ($) | B11: =DCF!C20

Sheet DCF
A1: Framework 1 — Traditional WACC-discounted DCF (intrinsic value)
A3: ($ in millions) | C3: FY2024A | D3: FY2025A | E3: FY2026E | F3: FY2027E | G3: FY2028E | H3: FY2029E | I3: FY2030E | J3: FY2031E | K3: FY2032E | L3: FY2033E | M3: FY2034E | N3: FY2035E
A5: Free cash flow ($M) | C5: ='Cash Flow'!C12 | D5: ='Cash Flow'!D12 | E5: ='Cash Flow'!E12 | F5: ='Cash Flow'!F12 | G5: ='Cash Flow'!G12 | H5: ='Cash Flow'!H12 | I5: ='Cash Flow'!I12 | J5: ='Cash Flow'!J12 | ... N5: ='Cash Flow'!N12
A6: Discount period (years from mid-FY26) | C6: 0 | D6: 0 | E6: 0.5 | F6: 1.5 | G6: 2.5 | H6: 3.5 | I6: 4.5 | J6: 5.5 | K6: 6.5 | L6: 7.5 | M6: 8.5 | N6: 9.5
A7: Discount factor @ WACC | C7: =1/(1+Drivers!C27)^C6 | D7: =1/(1+Drivers!C27)^D6 | E7: =1/(1+Drivers!C27)^E6 | F7: =1/(1+Drivers!C27)^F6 | G7: =1/(1+Drivers!C27)^G6 | H7: =1/(1+Drivers!C27)^H6 | I7: =1/(1+Drivers!C27)^I6 | J7: =1/(1+Drivers!C27)^J6 | K7: =1/(1+Drivers!C27)^K6 | L7: =1/(1+Drivers!C27)^L6 | M7: =1/(1+Drivers!C27)^M6 | N7: =1/(1+Drivers!C27)^N6
A8: PV of FCF | C8: =C5*C7 | D8: =D5*D7 | E8: =E5*E7 | F8: =F5*F7 | G8: =G5*G7 | H8: =H5*H7 | I8: =I5*I7 | J8: =J5*J7 | ... N8: =N5*N7
A10: Sum of PV (FCF, FY26E-FY35E) | C10: =SUM(E8:N8)
A11: Terminal FCF (FY35E base) | C11: =N5
A12: Terminal value (Gordon, g=4%) | C12: =C11*(1+Drivers!C28)/(Drivers!C27-Drivers!C28)
A13: PV of terminal value | C13: =C12*N7
A14: Enterprise value ($M) | C14: =C10+C13
A15: + Cash (post-IPO) | C15: 2080
A16: - Debt | C16: 0
A17: Equity value ($M) | C17: =C14+C15-C16
A18: / Shares (M, fully diluted) | C18: =Drivers!E19
A19: Implied price per share ($) | C19: =C17/C18
A20: Current trading price ($, Jun 4 2026) | C20: 68
A21: Premium / (discount) to intrinsic | C21: =C20/C19-1
A25: Framework 2 — Reverse-engineered: what must be true to justify $68?
A27: Current market cap ($M, fully diluted) | C27: =C20*C18
A28: - Cash | C28: =C15
A29: Implied EV ($M) | C29: =C27-C28
A31: Mature-state assumption (FY2035E)
A32: Target FY2035E EV/Revenue multiple (mature) | C32: 8
A33: Implied FY2035E revenue to clear $68 today | C33: =C29*(1+Drivers!C27)^9.5/C32
A34: Model FY2035E revenue | C34: =Drivers!N10
A35: Gap (implied / model) | C35: =C33/C34-1
A37: Implied 2035 share of $50B QC TAM | C37: 50000
A38: Required market share to clear $68 | C38: =C33/C37
A40: Sense check: today's revenue ranking vs implied 2035 share
A41: QNT FY25 revenue / FY35 implied revenue (10-yr CAGR) | C41: =(C33/Drivers!D10)^(1/10)-1

Sheet Cash Flow
A1: Cash Flow Statement ($M)
A3: ($ in millions) | C3: FY2024A | D3: FY2025A | E3: FY2026E | F3: FY2027E | G3: FY2028E | H3: FY2029E | I3: FY2030E | J3: FY2031E | K3: FY2032E | L3: FY2033E | M3: FY2034E | N3: FY2035E
A5: Net income (loss) | C5: ='Income Statement'!C19 | D5: ='Income Statement'!D19 | E5: ='Income Statement'!E19 | F5: ='Income Statement'!F19 | G5: ='Income Statement'!G19 | H5: ='Income Statement'!H19 | I5: ='Income Statement'!I19 | J5: ='Income Statement'!J19 | ... N5: ='Income Statement'!N19
A6: + Stock-based comp (~50% of R&D in early years) | C6: 0.55 | D6: 0.5 | E6: 0.45 | F6: 0.4 | G6: 0.35 | H6: 0.3 | I6: 0.27 | J6: 0.25 | K6: 0.22 | L6: 0.2 | M6: 0.18 | N6: 0.16
A7: + Stock-based comp ($) | C7: ='Income Statement'!C9*C6 | D7: ='Income Statement'!D9*D6 | E7: ='Income Statement'!E9*E6 | F7: ='Income Statement'!F9*F6 | G7: ='Income Statement'!G9*G6 | H7: ='Income Statement'!H9*H6 | I7: ='Income Statement'!I9*I6 | J7: ='Income Statement'!J9*J6 | ... N7: ='Income Statement'!N9*N6
A8: + D&A | C8: ='Income Statement'!C5*Drivers!C21 | D8: ='Income Statement'!D5*Drivers!D21 | E8: ='Income Statement'!E5*Drivers!E21 | F8: ='Income Statement'!F5*Drivers!F21 | G8: ='Income Statement'!G5*Drivers!G21 | H8: ='Income Statement'!H5*Drivers!H21 | I8: ='Income Statement'!I5*Drivers!I21 | J8: ='Income Statement'!J5*Drivers!J21 | ... N8: ='Income Statement'!N5*Drivers!N21
A9: Operating cash flow | C9: =C5+C7+C8 | D9: =D5+D7+D8 | E9: =E5+E7+E8 | F9: =F5+F7+F8 | G9: =G5+G7+G8 | H9: =H5+H7+H8 | I9: =I5+I7+I8 | J9: =J5+J7+J8 | ... N9: =N5+N7+N8
A11: Capex | C11: =-'Income Statement'!C5*Drivers!C20 | D11: =-'Income Statement'!D5*Drivers!D20 | E11: =-'Income Statement'!E5*Drivers!E20 | F11: =-'Income Statement'!F5*Drivers!F20 | G11: =-'Income Statement'!G5*Drivers!G20 | H11: =-'Income Statement'!H5*Drivers!H20 | I11: =-'Income Statement'!I5*Drivers!I20 | J11: =-'Income Statement'!J5*Drivers!J20 | ... N11: =-'Income Statement'!N5*Drivers!N20
A12: Free cash flow | C12: =C9+C11 | D12: =D9+D11 | E12: =E9+E11 | F12: =F9+F11 | G12: =G9+G11 | H12: =H9+H11 | I12: =I9+I11 | J12: =J9+J11 | ... N12: =N9+N11
A14: Financing — IPO proceeds (net) | C14: 0 | D14: 0 | E14: 1580 | F14: 0 | G14: 0 | H14: 0 | I14: 0 | J14: 0 | K14: 0 | L14: 0 | M14: 0 | N14: 0
A15: Beginning cash | C15: 502 | D15: =C17 | E15: =D17 | F15: =E17 | G15: =F17 | H15: =G17 | I15: =H17 | J15: =I17 | K15: =J17 | ... N15: =M17
A16: Change in cash | C16: =C12+C14 | D16: =D12+D14 | E16: =E12+E14 | F16: =F12+F14 | G16: =G12+G14 | H16: =H12+H14 | I16: =I12+I14 | J16: =J12+J14 | ... N16: =N12+N14
A17: Ending cash | C17: =C15+C16 | D17: =D15+D16 | E17: =E15+E16 | F17: =F15+F16 | G17: =G15+G16 | H17: =H15+H16 | I17: =I15+I16 | J17: =J15+J16 | ... N17: =N15+N16
A19: Cash runway check
A20: Years of cash at current burn | C20: =IF(C12>=0,"profitable",C17/(-C12)) | D20: =IF(D12>=0,"profitable",D17/(-D12)) | E20: =IF(E12>=0,"profitable",E17/(-E12)) | F20: =IF(F12>=0,"profitable",F17/(-F12)) | G20: =IF(G12>=0,"profitable",G17/(-G12)) | H20: =IF(H12>=0,"profitable",H17/(-H12)) | I20: =IF(I12>=0,"profitable",I17/(-I12)) | J20: =IF(J12>=0,"profitable",J17/(-J12)) | ... N20: =IF(N12>=0,"profitable",N17/(-N12))

Sheet Balance Sheet
A1: Balance Sheet ($M) — simplified
A3: ($ in millions) | C3: FY2024A | D3: FY2025A | E3: FY2026E | F3: FY2027E | G3: FY2028E | H3: FY2029E | I3: FY2030E | J3: FY2031E | K3: FY2032E | L3: FY2033E | M3: FY2034E | N3: FY2035E
A5: Cash & investments | C5: ='Cash Flow'!C17 | D5: ='Cash Flow'!D17 | E5: ='Cash Flow'!E17 | F5: ='Cash Flow'!F17 | G5: ='Cash Flow'!G17 | H5: ='Cash Flow'!H17 | I5: ='Cash Flow'!I17 | J5: ='Cash Flow'!J17 | ... N5: ='Cash Flow'!N17
A6: Other assets (PP&E + intangibles, est.) | C6: 200 | D6: 250 | E6: 320 | F6: 400 | G6: 500 | H6: 620 | I6: 760 | J6: 920 | K6: 1100 | L6: 1300 | M6: 1520 | N6: 1760
A7: Total assets | C7: =C5+C6 | D7: =D5+D6 | E7: =E5+E6 | F7: =F5+F6 | G7: =G5+G6 | H7: =H5+H6 | I7: =I5+I6 | J7: =J5+J6 | ... N7: =N5+N6
A9: Total liabilities (operating, est.) | C9: 80 | D9: 100 | E9: 140 | F9: 180 | G9: 220 | H9: 270 | I9: 320 | J9: 380 | K9: 450 | L9: 520 | M9: 600 | N9: 680
A10: Total stockholders' equity (plug) | C10: =C7-C9 | D10: =D7-D9 | E10: =E7-E9 | F10: =F7-F9 | G10: =G7-G9 | H10: =H7-H9 | I10: =I7-I9 | J10: =J7-J9 | ... N10: =N7-N9
A11: Check: TA = TL + TE | C11: =C7-C9-C10 | D11: =D7-D9-D10 | E11: =E7-E9-E10 | F11: =F7-F9-F10 | G11: =G7-G9-G10 | H11: =H7-H9-H10 | I11: =I7-I9-I10 | J11: =J7-J9-J10 | ... N11: =N7-N9-N10

Sheet Income Statement
A1: Income Statement (GAAP, $M)
A3: ($ in millions) | C3: FY2024A | D3: FY2025A | E3: FY2026E | F3: FY2027E | G3: FY2028E | H3: FY2029E | I3: FY2030E | J3: FY2031E | K3: FY2032E | L3: FY2033E | M3: FY2034E | N3: FY2035E
A5: Revenue | C5: =Drivers!C10 | D5: =Drivers!D10 | E5: =Drivers!E10 | F5: =Drivers!F10 | G5: =Drivers!G10 | H5: =Drivers!H10 | I5: =Drivers!I10 | J5: =Drivers!J10 | ... N5: =Drivers!N10
A6: Cost of revenue | C6: =C5*(1-Drivers!C14) | D6: =D5*(1-Drivers!D14) | E6: =E5*(1-Drivers!E14) | F6: =F5*(1-Drivers!F14) | G6: =G5*(1-Drivers!G14) | H6: =H5*(1-Drivers!H14) | I6: =I5*(1-Drivers!I14) | J6: =J5*(1-Drivers!J14) | ... N6: =N5*(1-Drivers!N14)
A7: Gross profit | C7: =C5-C6 | D7: =D5-D6 | E7: =E5-E6 | F7: =F5-F6 | G7: =G5-G6 | H7: =H5-H6 | I7: =I5-I6 | J7: =J5-J6 | ... N7: =N5-N6
A9: Research & development | C9: =C5*Drivers!C15 | D9: =D5*Drivers!D15 | E9: =E5*Drivers!E15 | F9: =F5*Drivers!F15 | G9: =G5*Drivers!G15 | H9: =H5*Drivers!H15 | I9: =I5*Drivers!I15 | J9: =J5*Drivers!J15 | ... N9: =N5*Drivers!N15
A10: Selling, general & administrative | C10: =C5*Drivers!C16 | D10: =D5*Drivers!D16 | E10: =E5*Drivers!E16 | F10: =F5*Drivers!F16 | G10: =G5*Drivers!G16 | H10: =H5*Drivers!H16 | I10: =I5*Drivers!I16 | J10: =J5*Drivers!J16 | ... N10: =N5*Drivers!N16
A11: Total operating expenses | C11: =C9+C10 | D11: =D9+D10 | E11: =E9+E10 | F11: =F9+F10 | G11: =G9+G10 | H11: =H9+H10 | I11: =I9+I10 | J11: =J9+J10 | ... N11: =N9+N10
A13: Operating income (loss) | C13: =C7-C11 | D13: =D7-D11 | E13: =E7-E11 | F13: =F7-F11 | G13: =G7-G11 | H13: =H7-H11 | I13: =I7-I11 | J13: =J7-J11 | ... N13: =N7-N11
A14: Operating margin % | C14: =C13/C5 | D14: =D13/D5 | E14: =E13/E5 | F14: =F13/F5 | G14: =G13/G5 | H14: =H13/H5 | I14: =I13/I5 | J14: =J13/J5 | ... N14: =N13/N5
A16: Interest income (on cash) | C16: 25 | D16: 28 | E16: 80 | F16: 75 | G16: 65 | H16: 55 | I16: 45 | J16: 35 | K16: 25 | L16: 15 | M16: 10 | N16: 5
A17: Pre-tax income (loss) | C17: =C13+C16 | D17: =D13+D16 | E17: =E13+E16 | F17: =F13+F16 | G17: =G13+G16 | H17: =H13+H16 | I17: =I13+I16 | J17: =J13+J16 | ... N17: =N13+N16
A18: Tax provision (cash 0% pre-profit, 21% post) | C18: =MAX(0,C17)*0.21 | D18: =MAX(0,D17)*0.21 | E18: =MAX(0,E17)*0.21 | F18: =MAX(0,F17)*0.21 | G18: =MAX(0,G17)*0.21 | H18: =MAX(0,H17)*0.21 | I18: =MAX(0,I17)*0.21 | J18: =MAX(0,J17)*0.21 | ... N18: =MAX(0,N17)*0.21
A19: Net income (loss) | C19: =C17-C18 | D19: =D17-D18 | E19: =E17-E18 | F19: =F17-F18 | G19: =G17-G18 | H19: =H17-H18 | I19: =I17-I18 | J19: =J17-J18 | ... N19: =N17-N18
A20: EPS (diluted, $) | C20: =C19/Drivers!C19 | D20: =D19/Drivers!D19 | E20: =E19/Drivers!E19 | F20: =F19/Drivers!F19 | G20: =G19/Drivers!G19 | H20: =H19/Drivers!H19 | I20: =I19/Drivers!I19 | J20: =J19/Drivers!J19 | ... N20: =N19/Drivers!N19

Sheet Drivers
A1: Quantinuum Inc. (QNT) — Drivers & Assumptions
A3: ($ in millions) | C3: FY2024A | D3: FY2025A | E3: FY2026E | F3: FY2027E | G3: FY2028E | H3: FY2029E | I3: FY2030E | J3: FY2031E | K3: FY2032E | L3: FY2033E | M3: FY2034E | N3: FY2035E
A5: Revenue build ($M)
A6: RIKEN system + maintenance | C6: 14.5 | D6: 18.5 | E6: 4 | F6: 2 | G6: 1 | H6: 0.5 | I6: 0 | J6: 0 | K6: 0 | L6: 0 | M6: 0 | N6: 0
A7: Helios cloud + on-prem (commercial) | C7: 4 | D7: 5 | E7: 22 | F7: 75 | G7: 180 | H7: 350 | I7: 580 | J7: 850 | K7: 1180 | L7: 1550 | M7: 1980 | N7: 2480
A8: Quantum Origin + InQuanto SaaS | C8: 2.5 | D8: 4 | E8: 8 | F8: 16 | G8: 32 | H8: 60 | I8: 100 | J8: 160 | K8: 240 | L8: 340 | M8: 460 | N8: 600
A9: Government / DARPA / CHIPS | C9: 2 | D9: 3.4 | E9: 6 | F9: 12 | G9: 20 | H9: 30 | I9: 45 | J9: 65 | K9: 90 | L9: 120 | M9: 160 | N9: 200
A10: Total revenue | C10: =SUM(C6:C9) | D10: =SUM(D6:D9) | E10: =SUM(E6:E9) | F10: =SUM(F6:F9) | G10: =SUM(G6:G9) | H10: =SUM(H6:H9) | I10: =SUM(I6:I9) | J10: =SUM(J6:J9) | ... N10: =SUM(N6:N9)
A11: YoY growth | D11: =D10/C10-1 | E11: =E10/D10-1 | F11: =F10/E10-1 | G11: =G10/F10-1 | H11: =H10/G10-1 | I11: =I10/H10-1 | J11: =J10/I10-1 | K11: =K10/J10-1 | ... N11: =N10/M10-1
A13: Operating model
A14: Gross margin % | C14: 0.3 | D14: 0.32 | E14: 0.38 | F14: 0.45 | G14: 0.52 | H14: 0.58 | I14: 0.62 | J14: 0.65 | K14: 0.67 | L14: 0.68 | M14: 0.69 | N14: 0.7
A15: R&D % of revenue | C15: 4.5 | D15: 5.4 | E15: 2.8 | F15: 1.2 | G15: 0.55 | H15: 0.32 | I15: 0.22 | J15: 0.16 | K15: 0.13 | L15: 0.11 | M15: 0.1 | N15: 0.09
A16: SG&A % of revenue | C16: 1.5 | D16: 1.8 | E16: 1.1 | F16: 0.55 | G16: 0.3 | H16: 0.2 | I16: 0.16 | J16: 0.14 | K16: 0.12 | L16: 0.11 | M16: 0.1 | N16: 0.1
A18: Capital structure & cash
A19: Shares outstanding (M, fully diluted) | C19: 200 | D19: 226 | E19: 253.9 | F19: 263 | G19: 273 | H19: 283 | I19: 293 | J19: 303 | K19: 313 | L19: 323 | M19: 333 | N19: 343
A20: Capex % of revenue | C20: 0.8 | D20: 0.65 | E20: 0.4 | F20: 0.25 | G20: 0.18 | H20: 0.14 | I20: 0.12 | J20: 0.1 | K20: 0.09 | L20: 0.08 | M20: 0.08 | N20: 0.07
A21: D&A % of revenue | C21: 0.5 | D21: 0.4 | E21: 0.28 | F21: 0.2 | G21: 0.15 | H21: 0.12 | I21: 0.1 | J21: 0.08 | K21: 0.07 | L21: 0.06 | M21: 0.06 | N21: 0.05
A23: WACC inputs
A24: Risk-free rate (10Y UST, Jun-26) | C24: 0.043
A25: Equity risk premium | C25: 0.055
A26: Beta (pre-profit quantum proxy) | C26: 2.1
A27: WACC = rf + beta * ERP | C27: =C24+C26*C25
A28: Terminal growth rate | C28: 0.04
