Workbook

Sheet Notes
A1: Comps notes
A3: PEER SET RATIONALE
A4: Comps statistics computed over IONQ, RGTI, QBTS (the 3 public quantum pure-plays).
A5: HON is a MEMO column — Honeywell still owns ~48% post-IPO, so worth attributing
A6: QNT's marginal value to HON's market cap; not a valuation comp.
A8: VALUATION INSIGHT
A9: • At $68, QNT trades at ~470-490x EV/FY25 revenue.
A10: • Peer median EV/FY25 (IONQ, RGTI, QBTS): ~530x — QNT is roughly IN LINE.
A11: • Peer median EV/TTM: ~720x — QNT trades at a DISCOUNT here.
A12: • The 'rich vs peers' narrative is wrong. The 'rich vs intrinsic DCF' narrative
A13: is correct (see QNT-Model.xlsx; +175% premium to traditional DCF).
A15: FOOTBALL FIELD
... A33: revenue and growth rows. QNT's own Q2 print is the first major catalyst.

Sheet Tech & Growth
A1: Technology, customers & growth
B3: QNT | C3: IONQ | D3: RGTI | E3: QBTS | F3: HON (memo)
B4: Target | C4: Trapped-ion direct comp | D4: Superconducting | E4: Annealing (specialty) | F4: Parent — 48% post-IPO
A6: Modality | B6: Trapped-ion (QCCD) | C6: Trapped-ion | D6: Superconducting | E6: Quantum annealing | F6: Industrial conglomerate
A7: Latest commercial system | B7: Helios (Nov 2025) | C7: Forte / Tempo (2026) | D7: Cepheus-108Q (Apr 2026) | E7: Advantage2 (May 2025) | F7: n/a
A8: Qubit count (latest) | B8: 98 (Helios) | C8: 64+ AQ; Tempo 5th gen | D8: 108 | E8: 4,400+ | F8: n/a
A9: 2-qubit gate fidelity | B9: 99.921% (Helios) | C9: 99.99% (lab) | D9: 99.1% on 108Q; 99.9% prototype | E9: n/a (annealer) | F9: n/a
A10: Quantum Volume record | B10: 2^25 (33M, Sept'25) | C10: n/d | D10: n/d | E10: n/a (annealer) | F10: n/a
A11: Next milestone | B11: Sol 2027 (192q) | C11: Tempo / 200k qubits | D11: 99.5% fidelity 2H'26 | E11: Quantum Circuits gate-model | F11: QNT IPO proceeds
A12: FTQC roadmap year | B12: 2029 (Apollo) | C12: 2028 functional test | D12: ~3 yrs to QC advantage | E12: QCI gate-model acquisition | F12: n/a
A13: Marquee customers | B13: RIKEN, JPMC, BMW, Amgen, MSFT, SoftBank | C13: AWS, AstraZeneca, NVIDIA, AFRL, ORNL | D13: Novera ($5.7M), DOE, AFRL, Japan QPU | E13: Mastercard, Lockheed, 135+ commercial | F13: Aerospace, defense, automation, energy
A14: Govt revenue exposure | B14: DARPA QBI Stage B, $100M CHIPS LOI | C14: DARPA HARQ + others | D14: DOE, AFRL | E14: Various govt | F14: Major defense
A15: Modality maturity assessment | B15: High fidelity; scaling the key risk | C15: Production-scale revenue | D15: Roadmap uncertain | E15: Annealer NOT gate-model; adding via M&A | F15: Diversified

Sheet Valuation
A1: Valuation multiples
B3: QNT | C3: IONQ | D3: RGTI | E3: QBTS | F3: HON (memo)
B4: Target | C4: Trapped-ion direct comp | D4: Superconducting | E4: Annealing (specialty) | F4: Parent — 48% post-IPO
A6: Enterprise value ($M) | B6: =Inputs!B11 | C6: =Inputs!C11 | D6: =Inputs!D11 | E6: =Inputs!E11 | F6: =Inputs!F11
A7: EV / FY2025 revenue | B7: =Inputs!B11/Inputs!B14 | C7: =Inputs!C11/Inputs!C14 | D7: =Inputs!D11/Inputs!D14 | E7: =Inputs!E11/Inputs!E14 | F7: =Inputs!F11/Inputs!F14
A8: EV / TTM revenue | B8: =Inputs!B11/Inputs!B16 | C8: =Inputs!C11/Inputs!C16 | D8: =Inputs!D11/Inputs!D16 | E8: =Inputs!E11/Inputs!E16 | F8: =Inputs!F11/Inputs!F16
A10: Peer-set stats (excl. target QNT and memo HON)
A11: Median EV / FY25 revenue | B11: =MEDIAN(C7:E7)
A12: Median EV / TTM revenue | B12: =MEDIAN(C8:E8)
A14: QNT premium / (discount) to peer median
A15: on FY2025 revenue | B15: =B7/B11-1
A16: on TTM revenue | B16: =B8/B12-1
A19: Football field — implied price per QNT share
A20: Low (RGTI multiple ~726x; we hold rev constant) | B20: =(D7*Inputs!B14+Inputs!B9)/Inputs!B7
A21: Mid (median peer multiple) | B21: =(B11*Inputs!B14+Inputs!B9)/Inputs!B7
A22: High (apply QBTS multiple ~754x) | B22: =(E7*Inputs!B14+Inputs!B9)/Inputs!B7
A23: IONQ-anchored (~120x — lowest peer) | B23: =(C7*Inputs!B14+Inputs!B9)/Inputs!B7
A24: Current trading price | B24: =Inputs!B6

Sheet Operating Metrics
A1: Operating metrics & profitability
B3: QNT | C3: IONQ | D3: RGTI | E3: QBTS | F3: HON (memo)
B4: Target | C4: Trapped-ion direct comp | D4: Superconducting | E4: Annealing (specialty) | F4: Parent — 48% post-IPO
A6: Latest-Q non-GAAP / Adj. EBITDA ($M) | B6: -130 | C6: -96.8 | D6: -14.7 | E6: -18.4 | F6: 9200
A7: R&D ($M, latest year) | B7: 165.4 | C7: 254 | D7: 35.7 | E7: 88 | F7: 1500
A8: R&D / revenue | B8: =B7/B14 | C8: =C7/C14 | D8: =D7/D14 | E8: =E7/E14 | F8: =F7/F14
A9: Cash burn (annualized FCF, $M) | B9: -440 | C9: -350 | D9: -55 | E9: -80 | F9: 6500
A10: Years of cash runway (cash / burn) | B10: =IF(B9>=0,99,Inputs!B9/(-B9)) | C10: =IF(C9>=0,99,Inputs!C9/(-C9)) | D10: =IF(D9>=0,99,Inputs!D9/(-D9)) | E10: =IF(E9>=0,99,Inputs!E9/(-E9)) | F10: =IF(F9>=0,99,Inputs!F9/(-F9))
A12: Customer concentration (top customer % rev) | B12: 0.6 | C12: 0.2 | D12: 0.3 | E12: 0.15 | F12: 0.1

Sheet Inputs
A1: Quantum-computing comps — Inputs (as of June 4, 2026)
B3: QNT | C3: IONQ | D3: RGTI | E3: QBTS | F3: HON (memo)
B4: Target | C4: Trapped-ion direct comp | D4: Superconducting | E4: Annealing (specialty) | F4: Parent — 48% post-IPO
A6: Share price ($, Jun 3-4 2026) | B6: 68 | C6: 68.21 | D6: 24.1 | E6: 27.09 | F6: 213
A7: Shares outstanding (M, fully diluted) | B7: 253.9 | C7: 373.2 | D7: 325 | E7: 369.9 | F7: 650
A8: Market cap ($M) | B8: =B6*B7 | C8: =C6*C7 | D8: =D6*D7 | E8: =E6*E7 | F8: =F6*F7
A9: Cash & investments ($M) | B9: 2080 | C9: 3100 | D9: 569 | E9: 588 | F9: 11000
A10: Debt ($M) | B10: 0 | C10: 0 | D10: 0 | E10: 0 | F10: 22000
A11: Enterprise value ($M) | B11: =B8-B9+B10 | C11: =C8-C9+C10 | D11: =D8-D9+D10 | E11: =E8-E9+E10 | F11: =F8-F9+F10
A13: Revenue
A14: FY 2025 revenue ($M) | B14: 30.9 | C14: 130 | D14: 7.1 | E14: 24.6 | F14: 38500
A15: Q1 2026 revenue ($M) | B15: 5.2 | C15: 64.7 | D15: 4.4 | E15: 2.9 | F15: 9600
A16: TTM revenue ($M, est.) | B16: 32.6 | C16: 187.1 | D16: 10 | E16: 12.5 | F16: 38500
A18: Most recent quarter YoY growth | B18: -0.13 | C18: 7.55 | D18: 1.99 | E18: -0.81 | F18: 0.04
