Workbook

Sheet Drivers
A1: ALPHABET (GOOG/GOOGL) — INTEGRATED MODEL: DRIVERS & ASSUMPTIONS
A2: As of June 3, 2026 | $M unless noted | Blue=input, Black=formula | Calendar fiscal year
A4: SEGMENT REVENUE BUILD ($M)
A5: ($ in millions) | C5: FY2023A | D5: FY2024A | E5: FY2025A | F5: FY2026E | G5: FY2027E | H5: FY2028E | I5: FY2029E | J5: FY2030E
A6: Google Services (Search, YouTube, Other) | C6: 272500 | D6: 304922 | E6: 342700 | F6: 393100 | G6: 432400 | H6: 471300 | I6: 509000 | J6: 545600
A7: Google Cloud | C7: 33088 | D7: 43200 | E7: 58700 | F7: 92000 | G7: 132000 | H7: 178000 | I7: 222000 | J7: 266000
A8: Other Bets (Waymo etc.) | C8: 1527 | D8: 1539 | E8: 1537 | F8: 1800 | G8: 2100 | H8: 2500 | I8: 3000 | J8: 3600
A9: Total revenue | C9: =SUM(C6:C8) | D9: =SUM(D6:D8) | E9: =SUM(E6:E8) | F9: =SUM(F6:F8) | G9: =SUM(G6:G8) | H9: =SUM(H6:H8) | I9: =SUM(I6:I8) | J9: =SUM(J6:J8)
A10: Total revenue growth % | C10: n/a | D10: =D9/C9-1 | E10: =E9/D9-1 | F10: =F9/E9-1 | G10: =G9/F9-1 | H10: =H9/G9-1 | I10: =I9/H9-1 | J10: =J9/I9-1
A12: SEGMENT OPERATING MARGINS
A13: ($ in millions) | C13: FY2023A | D13: FY2024A | E13: FY2025A | F13: FY2026E | G13: FY2027E | H13: FY2028E | I13: FY2029E | J13: FY2030E
A14: Google Services op margin % | C14: 0.45 | D14: 0.45 | E14: 0.45 | F14: 0.45 | G14: 0.45 | H14: 0.45 | I14: 0.45 | J14: 0.45
A15: Google Cloud op margin % | C15: 0.052 | D15: 0.14 | E15: 0.237 | F15: 0.3 | G15: 0.32 | H15: 0.34 | I15: 0.35 | J15: 0.36
A16: Other Bets op margin % (loss) | C16: -2.93 | D16: -3 | E16: -4.88 | F16: -3.5 | G16: -2.5 | H16: -1.5 | I16: -1 | J16: -0.5
A17: Corporate / unallocated ($M) | C17: 7000 | D17: 7500 | E17: 8000 | F17: 9000 | G17: 10000 | H17: 11000 | I17: 12000 | J17: 13000
A19: Total operating income (EBIT) | C19: =C6*C14+C7*C15+C8*C16-C17 | D19: =D6*D14+D7*D15+D8*D16-D17 | E19: =E6*E14+E7*E15+E8*E16-E17 | F19: =F6*F14+F7*F15+F8*F16-F17 | G19: =G6*G14+G7*G15+G8*G16-G17 | H19: =H6*H14+H7*H15+H8*H16-H17 | I19: =I6*I14+I7*I15+I8*I16-I17 | J19: =J6*J14+J7*J15+J8*J16-J17
A21: D&A / CAPEX / TAX / NWC
A22: ($ in millions) | C22: FY2023A | D22: FY2024A | E22: FY2025A | F22: FY2026E | G22: FY2027E | H22: FY2028E | I22: FY2029E | J22: FY2030E
A23: D&A ($M) | C23: 11946 | D23: 15311 | E23: 22000 | F23: 38000 | G23: 58000 | H23: 76000 | I23: 90000 | J23: 100000
A24: Capex ($M) | C24: 32251 | D24: 52535 | E24: 92000 | F24: 185000 | G24: 200000 | H24: 180000 | I24: 160000 | J24: 150000
A25: Cash tax rate % | C25: 0.155 | D25: 0.16 | E25: 0.16 | F25: 0.18 | G25: 0.2 | H25: 0.21 | I25: 0.21 | J25: 0.21
A26: Incr. NWC % of rev growth | C26: 0.05 | D26: 0.05 | E26: 0.05 | F26: 0.05 | G26: 0.05 | H26: 0.05 | I26: 0.05 | J26: 0.05
A28: MARKET DATA & WACC INPUTS
A29: Current share price ($) | C29: 357.73
A30: Diluted shares (M) | C30: 12120
A31: Total debt ($M) | C31: 46500
A32: Cash & marketable securities ($M) | C32: 126800
A33: Risk-free rate % | C33: 0.043
A34: Equity risk premium % | C34: 0.05
A35: Beta | C35: 1
A36: Pre-tax cost of debt % | C36: 0.045
A37: Terminal growth rate % | C37: 0.03
A39: WACC (computed)
A40: Cost of equity | C40: =C33+C35*C34
A41: After-tax cost of debt | C41: =C36*(1-E25)
A42: Market value of equity ($M) | C42: =C29*C30
A43: Net debt / (cash) ($M) | C43: =C31-C32
A44: Equity weight | C44: =C42/(C42+C31)
A45: Debt weight | C45: =C31/(C42+C31)
A46: WACC | C46: =C44*C40+C45*C41

Sheet Income Statement
A1: INCOME STATEMENT ($M)
A4: ($ in millions) | C4: FY2023A | D4: FY2024A | E4: FY2025A | F4: FY2026E | G4: FY2027E | H4: FY2028E | I4: FY2029E | J4: FY2030E
A5: Total revenue | C5: =Drivers!C9 | D5: =Drivers!D9 | E5: =Drivers!E9 | F5: =Drivers!F9 | G5: =Drivers!G9 | H5: =Drivers!H9 | I5: =Drivers!I9 | J5: =Drivers!J9
A7: Operating income (EBIT) | C7: =Drivers!C19 | D7: =Drivers!D19 | E7: =Drivers!E19 | F7: =Drivers!F19 | G7: =Drivers!G19 | H7: =Drivers!H19 | I7: =Drivers!I19 | J7: =Drivers!J19
A8: (+) D&A | C8: =Drivers!C23 | D8: =Drivers!D23 | E8: =Drivers!E23 | F8: =Drivers!F23 | G8: =Drivers!G23 | H8: =Drivers!H23 | I8: =Drivers!I23 | J8: =Drivers!J23
A9: EBITDA | C9: =C7+C8 | D9: =D7+D8 | E9: =E7+E8 | F9: =F7+F8 | G9: =G7+G8 | H9: =H7+H8 | I9: =I7+I8 | J9: =J7+J8
A10: (-) Net interest expense (or +income) | C10: -3050 | D10: -4000 | E10: -5000 | F10: =Drivers!F24/40 | G10: =Drivers!G24/40 | H10: =Drivers!H24/40 | I10: =Drivers!I24/40 | J10: =Drivers!J24/40
A11: Pre-tax income | C11: =C9-C8-C10 | D11: =D9-D8-D10 | E11: =E9-E8-E10 | F11: =F9-F8-F10 | G11: =G9-G8-G10 | H11: =H9-H8-H10 | I11: =I9-I8-I10 | J11: =J9-J8-J10
A12: (-) Income taxes | C12: =C11*Drivers!C25 | D12: =D11*Drivers!D25 | E12: =E11*Drivers!E25 | F12: =F11*Drivers!F25 | G12: =G11*Drivers!G25 | H12: =H11*Drivers!H25 | I12: =I11*Drivers!I25 | J12: =J11*Drivers!J25
A13: Net income (GAAP) | C13: =C11-C12 | D13: =D11-D12 | E13: =E11-E12 | F13: =F11-F12 | G13: =G11-G12 | H13: =H11-H12 | I13: =I11-I12 | J13: =J11-J12
A14: Net margin % | C14: =C13/C5 | D14: =D13/D5 | E14: =E13/E5 | F14: =F13/F5 | G14: =G13/G5 | H14: =H13/H5 | I14: =I13/I5 | J14: =J13/J5

Sheet Balance Sheet
A1: BALANCE SHEET (summary, $M)
A4: ($ in millions) | C4: FY2023A | D4: FY2024A | E4: FY2025A | F4: FY2026E | G4: FY2027E | H4: FY2028E | I4: FY2029E | J4: FY2030E
A5: Cash + marketable securities | C5: 110900 | D5: 95700 | E5: 126800 | F5: =E5+'Cash Flow'!F13-F10-F11 | G5: =F5+'Cash Flow'!G13-G10-G11 | H5: =G5+'Cash Flow'!H13-H10-H11 | I5: =H5+'Cash Flow'!I13-I10-I11 | J5: =I5+'Cash Flow'!J13-J10-J11
A6: Other assets (plug) | C6: =C7+C8-C5 | D6: =D7+D8-D5 | E6: =E7+E8-E5 | F6: =F7+F8-F5 | G6: =G7+G8-G5 | H6: =H7+H8-H5 | I6: =I7+I8-I5 | J6: =J7+J8-J5
A7: Total debt | C7: 13253 | D7: 10883 | E7: 46500 | F7: =E7 | G7: =F7 | H7: =G7 | I7: =H7 | J7: =I7
A8: Shareholders' equity | C8: 283379 | D8: 325084 | E8: 365000 | F8: =E8+'Income Statement'!F13-F11-F10 | G8: =F8+'Income Statement'!G13-G11-G10 | H8: =G8+'Income Statement'!H13-H11-H10 | I8: =H8+'Income Statement'!I13-I11-I10 | J8: =I8+'Income Statement'!J13-J11-J10
A9: Net cash (debt) | C9: =C5-C7 | D9: =D5-D7 | E9: =E5-E7 | F9: =F5-F7 | G9: =G5-G7 | H9: =H5-H7 | I9: =I5-I7 | J9: =J5-J7
A10: Equity issuance/(repurchase) in year | F10: -84750 | G10: 0 | H10: 0 | I10: 0 | J10: 0
A11: Dividends + buybacks (cash out) | F11: 50000 | G11: 60000 | H11: 70000 | I11: 80000 | J11: 90000

Sheet Cash Flow
A1: CASH FLOW & FREE CASH FLOW ($M)
A4: ($ in millions) | C4: FY2023A | D4: FY2024A | E4: FY2025A | F4: FY2026E | G4: FY2027E | H4: FY2028E | I4: FY2029E | J4: FY2030E
A5: EBIT | C5: ='Income Statement'!C7 | D5: ='Income Statement'!D7 | E5: ='Income Statement'!E7 | F5: ='Income Statement'!F7 | G5: ='Income Statement'!G7 | H5: ='Income Statement'!H7 | I5: ='Income Statement'!I7 | J5: ='Income Statement'!J7
A6: (-) Cash taxes on EBIT | C6: =C5*Drivers!C25 | D6: =D5*Drivers!D25 | E6: =E5*Drivers!E25 | F6: =F5*Drivers!F25 | G6: =G5*Drivers!G25 | H6: =H5*Drivers!H25 | I6: =I5*Drivers!I25 | J6: =J5*Drivers!J25
A7: NOPAT | C7: =C5-C6 | D7: =D5-D6 | E7: =E5-E6 | F7: =F5-F6 | G7: =G5-G6 | H7: =H5-H6 | I7: =I5-I6 | J7: =J5-J6
A8: (+) D&A | C8: =Drivers!C23 | D8: =Drivers!D23 | E8: =Drivers!E23 | F8: =Drivers!F23 | G8: =Drivers!G23 | H8: =Drivers!H23 | I8: =Drivers!I23 | J8: =Drivers!J23
A9: (-) Capex | C9: =Drivers!C24 | D9: =Drivers!D24 | E9: =Drivers!E24 | F9: =Drivers!F24 | G9: =Drivers!G24 | H9: =Drivers!H24 | I9: =Drivers!I24 | J9: =Drivers!J24
A10: (-) Increase in net working capital | C10: =0 | D10: =(Drivers!D9-Drivers!C9)*Drivers!D26 | E10: =(Drivers!E9-Drivers!D9)*Drivers!E26 | F10: =(Drivers!F9-Drivers!E9)*Drivers!F26 | G10: =(Drivers!G9-Drivers!F9)*Drivers!G26 | H10: =(Drivers!H9-Drivers!G9)*Drivers!H26 | I10: =(Drivers!I9-Drivers!H9)*Drivers!I26 | J10: =(Drivers!J9-Drivers!I9)*Drivers!J26
A11: Unlevered free cash flow | C11: =C7+C8-C9-C10 | D11: =D7+D8-D9-D10 | E11: =E7+E8-E9-E10 | F11: =F7+F8-F9-F10 | G11: =G7+G8-G9-G10 | H11: =H7+H8-H9-H10 | I11: =I7+I8-I9-I10 | J11: =J7+J8-J9-J10
A12: (-) After-tax net interest | C12: ='Income Statement'!C10*(1-Drivers!C25) | D12: ='Income Statement'!D10*(1-Drivers!D25) | E12: ='Income Statement'!E10*(1-Drivers!E25) | F12: ='Income Statement'!F10*(1-Drivers!F25) | G12: ='Income Statement'!G10*(1-Drivers!G25) | H12: ='Income Statement'!H10*(1-Drivers!H25) | I12: ='Income Statement'!I10*(1-Drivers!I25) | J12: ='Income Statement'!J10*(1-Drivers!J25)
A13: Levered free cash flow | C13: =C11-C12 | D13: =D11-D12 | E13: =E11-E12 | F13: =F11-F12 | G13: =G11-G12 | H13: =H11-H12 | I13: =I11-I12 | J13: =J11-J12
A14: Unlevered FCF margin % | C14: =C11/Drivers!C9 | D14: =D11/Drivers!D9 | E14: =E11/Drivers!E9 | F14: =F11/Drivers!F9 | G14: =G11/Drivers!G9 | H14: =H11/Drivers!H9 | I14: =I11/Drivers!I9 | J14: =J11/Drivers!J9

Sheet DCF
A1: DISCOUNTED CASH FLOW VALUATION
A4: Projection year | B4: FY2026E | C4: FY2027E | D4: FY2028E | E4: FY2029E | F4: FY2030E
A5: Period (n) | B5: =1 | C5: =2 | D5: =3 | E5: =4 | F5: =5
A6: Unlevered FCF | B6: ='Cash Flow'!F11 | C6: ='Cash Flow'!G11 | D6: ='Cash Flow'!H11 | E6: ='Cash Flow'!I11 | F6: ='Cash Flow'!J11
A7: Discount factor @ WACC | B7: =1/(1+Drivers!C46)^B5 | C7: =1/(1+Drivers!C46)^C5 | D7: =1/(1+Drivers!C46)^D5 | E7: =1/(1+Drivers!C46)^E5 | F7: =1/(1+Drivers!C46)^F5
A8: PV of unlevered FCF | B8: =B6*B7 | C8: =C6*C7 | D8: =D6*D7 | E8: =E6*E7 | F8: =F6*F7
A10: Sum of PV of explicit FCF (FY26-30) | C10: =SUM(B8:F8)
A11: Terminal-year FCF (FY2030) | C11: =F6
A12: Terminal value (Gordon) | C12: =F6*(1+Drivers!C37)/(Drivers!C46-Drivers!C37)
A13: PV of terminal value | C13: =C12*F7
A14: Enterprise value | C14: =C10+C13
A15: (+) Net cash (subtract net debt) | C15: =Drivers!C32-Drivers!C31
A16: Equity value | C16: =C14+C15
A17: Diluted shares (M) | C17: =Drivers!C30
A18: Implied value per share ($) | C18: =C16/C17
A19: Current share price ($) | C19: =Drivers!C29
A20: Upside / (downside) to current | C20: =C18/C19-1
A21: TV as % of enterprise value | C21: =C13/C14
A22: SENSITIVITY — Implied $/share: WACC (down) x Terminal growth (across)
B23: Terminal g → | C23: 0.02 | D23: 0.025 | E23: 0.03 | F23: 0.035 | G23: 0.04
A24: WACC ↓ | B24: 0.08 | C24: =(($B$6/(1+$B$24)^1+$C$6/(1+$B$24)^2+$D$6/(1+$B$24)^3+$E$6/(1+$B$24)^4+$F$6/(1+$B$24)^5)+(($F$6*(1+C$23)/($B$24-C$23))/(1+$B$24)^5)+Drivers!$C$32-Drivers!$C$31)/Drivers!$C$30 | D24: =(($B$6/(1+$B$24)^1+$C$6/(1+$B$24)^2+$D$6/(1+$B$24)^3+$E$6/(1+$B$24)^4+$F$6/(1+$B$24)^5)+(($F$6*(1+D$23)/($B$24-D$23))/(1+$B$24)^5)+Drivers!$C$32-Drivers!$C$31)/Drivers!$C$30 | E24: =(($B$6/(1+$B$24)^1+$C$6/(1+$B$24)^2+$D$6/(1+$B$24)^3+$E$6/(1+$B$24)^4+$F$6/(1+$B$24)^5)+(($F$6*(1+E$23)/($B$24-E$23))/(1+$B$24)^5)+Drivers!$C$32-Drivers!$C$31)/Drivers!$C$30 | F24: =(($B$6/(1+$B$24)^1+$C$6/(1+$B$24)^2+$D$6/(1+$B$24)^3+$E$6/(1+$B$24)^4+$F$6/(1+$B$24)^5)+(($F$6*(1+F$23)/($B$24-F$23))/(1+$B$24)^5)+Drivers!$C$32-Drivers!$C$31)/Drivers!$C$30 | G24: =(($B$6/(1+$B$24)^1+$C$6/(1+$B$24)^2+$D$6/(1+$B$24)^3+$E$6/(1+$B$24)^4+$F$6/(1+$B$24)^5)+(($F$6*(1+G$23)/($B$24-G$23))/(1+$B$24)^5)+Drivers!$C$32-Drivers!$C$31)/Drivers!$C$30
B25: 0.085 | C25: =(($B$6/(1+$B$25)^1+$C$6/(1+$B$25)^2+$D$6/(1+$B$25)^3+$E$6/(1+$B$25)^4+$F$6/(1+$B$25)^5)+(($F$6*(1+C$23)/($B$25-C$23))/(1+$B$25)^5)+Drivers!$C$32-Drivers!$C$31)/Drivers!$C$30 | D25: =(($B$6/(1+$B$25)^1+$C$6/(1+$B$25)^2+$D$6/(1+$B$25)^3+$E$6/(1+$B$25)^4+$F$6/(1+$B$25)^5)+(($F$6*(1+D$23)/($B$25-D$23))/(1+$B$25)^5)+Drivers!$C$32-Drivers!$C$31)/Drivers!$C$30 | E25: =(($B$6/(1+$B$25)^1+$C$6/(1+$B$25)^2+$D$6/(1+$B$25)^3+$E$6/(1+$B$25)^4+$F$6/(1+$B$25)^5)+(($F$6*(1+E$23)/($B$25-E$23))/(1+$B$25)^5)+Drivers!$C$32-Drivers!$C$31)/Drivers!$C$30 | F25: =(($B$6/(1+$B$25)^1+$C$6/(1+$B$25)^2+$D$6/(1+$B$25)^3+$E$6/(1+$B$25)^4+$F$6/(1+$B$25)^5)+(($F$6*(1+F$23)/($B$25-F$23))/(1+$B$25)^5)+Drivers!$C$32-Drivers!$C$31)/Drivers!$C$30 | G25: =(($B$6/(1+$B$25)^1+$C$6/(1+$B$25)^2+$D$6/(1+$B$25)^3+$E$6/(1+$B$25)^4+$F$6/(1+$B$25)^5)+(($F$6*(1+G$23)/($B$25-G$23))/(1+$B$25)^5)+Drivers!$C$32-Drivers!$C$31)/Drivers!$C$30
B26: 0.09 | C26: =(($B$6/(1+$B$26)^1+$C$6/(1+$B$26)^2+$D$6/(1+$B$26)^3+$E$6/(1+$B$26)^4+$F$6/(1+$B$26)^5)+(($F$6*(1+C$23)/($B$26-C$23))/(1+$B$26)^5)+Drivers!$C$32-Drivers!$C$31)/Drivers!$C$30 | D26: =(($B$6/(1+$B$26)^1+$C$6/(1+$B$26)^2+$D$6/(1+$B$26)^3+$E$6/(1+$B$26)^4+$F$6/(1+$B$26)^5)+(($F$6*(1+D$23)/($B$26-D$23))/(1+$B$26)^5)+Drivers!$C$32-Drivers!$C$31)/Drivers!$C$30 | E26: =(($B$6/(1+$B$26)^1+$C$6/(1+$B$26)^2+$D$6/(1+$B$26)^3+$E$6/(1+$B$26)^4+$F$6/(1+$B$26)^5)+(($F$6*(1+E$23)/($B$26-E$23))/(1+$B$26)^5)+Drivers!$C$32-Drivers!$C$31)/Drivers!$C$30 | F26: =(($B$6/(1+$B$26)^1+$C$6/(1+$B$26)^2+$D$6/(1+$B$26)^3+$E$6/(1+$B$26)^4+$F$6/(1+$B$26)^5)+(($F$6*(1+F$23)/($B$26-F$23))/(1+$B$26)^5)+Drivers!$C$32-Drivers!$C$31)/Drivers!$C$30 | G26: =(($B$6/(1+$B$26)^1+$C$6/(1+$B$26)^2+$D$6/(1+$B$26)^3+$E$6/(1+$B$26)^4+$F$6/(1+$B$26)^5)+(($F$6*(1+G$23)/($B$26-G$23))/(1+$B$26)^5)+Drivers!$C$32-Drivers!$C$31)/Drivers!$C$30
B27: 0.095 | C27: =(($B$6/(1+$B$27)^1+$C$6/(1+$B$27)^2+$D$6/(1+$B$27)^3+$E$6/(1+$B$27)^4+$F$6/(1+$B$27)^5)+(($F$6*(1+C$23)/($B$27-C$23))/(1+$B$27)^5)+Drivers!$C$32-Drivers!$C$31)/Drivers!$C$30 | D27: =(($B$6/(1+$B$27)^1+$C$6/(1+$B$27)^2+$D$6/(1+$B$27)^3+$E$6/(1+$B$27)^4+$F$6/(1+$B$27)^5)+(($F$6*(1+D$23)/($B$27-D$23))/(1+$B$27)^5)+Drivers!$C$32-Drivers!$C$31)/Drivers!$C$30 | E27: =(($B$6/(1+$B$27)^1+$C$6/(1+$B$27)^2+$D$6/(1+$B$27)^3+$E$6/(1+$B$27)^4+$F$6/(1+$B$27)^5)+(($F$6*(1+E$23)/($B$27-E$23))/(1+$B$27)^5)+Drivers!$C$32-Drivers!$C$31)/Drivers!$C$30 | F27: =(($B$6/(1+$B$27)^1+$C$6/(1+$B$27)^2+$D$6/(1+$B$27)^3+$E$6/(1+$B$27)^4+$F$6/(1+$B$27)^5)+(($F$6*(1+F$23)/($B$27-F$23))/(1+$B$27)^5)+Drivers!$C$32-Drivers!$C$31)/Drivers!$C$30 | G27: =(($B$6/(1+$B$27)^1+$C$6/(1+$B$27)^2+$D$6/(1+$B$27)^3+$E$6/(1+$B$27)^4+$F$6/(1+$B$27)^5)+(($F$6*(1+G$23)/($B$27-G$23))/(1+$B$27)^5)+Drivers!$C$32-Drivers!$C$31)/Drivers!$C$30
B28: 0.1 | C28: =(($B$6/(1+$B$28)^1+$C$6/(1+$B$28)^2+$D$6/(1+$B$28)^3+$E$6/(1+$B$28)^4+$F$6/(1+$B$28)^5)+(($F$6*(1+C$23)/($B$28-C$23))/(1+$B$28)^5)+Drivers!$C$32-Drivers!$C$31)/Drivers!$C$30 | D28: =(($B$6/(1+$B$28)^1+$C$6/(1+$B$28)^2+$D$6/(1+$B$28)^3+$E$6/(1+$B$28)^4+$F$6/(1+$B$28)^5)+(($F$6*(1+D$23)/($B$28-D$23))/(1+$B$28)^5)+Drivers!$C$32-Drivers!$C$31)/Drivers!$C$30 | E28: =(($B$6/(1+$B$28)^1+$C$6/(1+$B$28)^2+$D$6/(1+$B$28)^3+$E$6/(1+$B$28)^4+$F$6/(1+$B$28)^5)+(($F$6*(1+E$23)/($B$28-E$23))/(1+$B$28)^5)+Drivers!$C$32-Drivers!$C$31)/Drivers!$C$30 | F28: =(($B$6/(1+$B$28)^1+$C$6/(1+$B$28)^2+$D$6/(1+$B$28)^3+$E$6/(1+$B$28)^4+$F$6/(1+$B$28)^5)+(($F$6*(1+F$23)/($B$28-F$23))/(1+$B$28)^5)+Drivers!$C$32-Drivers!$C$31)/Drivers!$C$30 | G28: =(($B$6/(1+$B$28)^1+$C$6/(1+$B$28)^2+$D$6/(1+$B$28)^3+$E$6/(1+$B$28)^4+$F$6/(1+$B$28)^5)+(($F$6*(1+G$23)/($B$28-G$23))/(1+$B$28)^5)+Drivers!$C$32-Drivers!$C$31)/Drivers!$C$30
A30: Center cell (WACC 9.0% / g 3.0%) = base case; cross-check vs C18 implied per share.

Sheet Notes
A1: GOOG MODEL — METHODOLOGY & CAVEATS
A3: Methodology
A4: Integrated 3-statement model feeding unlevered DCF. Drivers tab drives everything.
A5: Revenue split into Google Services, Google Cloud, Other Bets — with explicit segment margins.
A6: Cloud is the marginal-mix story: 5%(23) → 14%(24) → 24%(25) → 30%(26E) → 36%(30E) op margin.
A7: Capex modeled at the announced $180-190B FY26 ramp (back-end loaded per Q1 $22.4B actual),
A8: tapering to ~$150-200B/yr through FY30 as build-out phase moderates.
A10: Base case stance
A11: GOOG is the unusual case: AI capex is dilutive near-term, but Cloud margin expansion + scale
A12: more than offsets. Base case: Cloud margin reaches 30% in FY26 (vs Q1 26 actual 32.9%),
A13: tapers up to 36% by FY30. WACC ~9.0%, terminal g 3.0%.
A14: Headwinds priced: ~$85B June 2026 equity raise (Berkshire pp + ATM); DOJ search remedies
... A24: Research / decision-framing only — NOT investment advice.
