Workbook

Sheet Inputs
A1: MEGA-CAP TECH — COMPARABLE COMPANY ANALYSIS (GOOG target)
A2: Alphabet (GOOG) • Meta Platforms (META) • Microsoft (MSFT) • Amazon (AMZN) • Netflix (NFLX) • The Trade Desk (TTD) • Reddit (RDDT)
A3: As of June 3, 2026 | $M except ratios | Stats over the 4 mega-cap peers (META, MSFT, AMZN, NFLX); GOOG=target; TTD, RDDT = ads-pure memo
A5: RAW INPUTS — cell comments cite source / assumption
A6: Company | B6: Ticker | C6: Mkt Cap | D6: Net Debt | E6: Revenue (TTM) | F6: Rev Growth % | G6: Gross Margin % | H6: EBITDA (TTM) | I6: Net Income (TTM) | J6: Fwd P/E | K6: Role
A7: Alphabet | B7: GOOG | C7: 4335000 | D7: -80300 | E7: 425100 | F7: 0.22 | G7: 0.58 | H7: 155000 | I7: 137000 | J7: 24 | K7: TARGET
A8: Meta Platforms | B8: META | C8: 1550000 | D8: -40000 | E8: 223000 | F8: 0.33 | G8: 0.82 | H8: 110000 | I8: 71000 | J8: 18.2 | K8: MEGA-CAP
A9: Microsoft | B9: MSFT | C9: 4720000 | D9: -30000 | E9: 318300 | F9: 0.18 | G9: 0.68 | H9: 274000 | I9: 125200 | J9: 22.6 | K9: MEGA-CAP
A10: Amazon | B10: AMZN | C10: 2700000 | D10: 66000 | E10: 742800 | F10: 0.17 | G10: 0.5 | H10: 145700 | I10: 91000 | J10: 30 | K10: MEGA-CAP
A11: Netflix | B11: NFLX | C11: 400000 | D11: 4450 | E11: 46900 | F11: 0.16 | G11: 0.52 | H11: 31100 | I11: 11000 | J11: 26 | K11: MEGA-CAP
A12: The Trade Desk | B12: TTD | C12: 10900 | D12: -1700 | E12: 2960 | F12: 0.12 | G12: 0.736 | H12: 900 | I12: 435 | J12: 11 | K12: ADS-PURE (memo)
A13: Reddit | B13: RDDT | C13: 30000 | D13: -2000 | E13: 2200 | F13: 0.69 | G13: 0.915 | H13: 545 | I13: 530 | J13: 33 | K13: ADS-PURE (memo)

Sheet Operating Metrics
A1: OPERATING METRICS
A6: Company | B6: Revenue (TTM) | C6: Rev Growth (YoY) | D6: Gross Margin | E6: EBITDA (TTM) | F6: EBITDA Margin
A7: Alphabet | B7: =Inputs!E7 | C7: =Inputs!F7 | D7: =Inputs!G7 | E7: =Inputs!H7 | F7: =Inputs!H7/Inputs!E7
A8: Meta Platforms | B8: =Inputs!E8 | C8: =Inputs!F8 | D8: =Inputs!G8 | E8: =Inputs!H8 | F8: =Inputs!H8/Inputs!E8
A9: Microsoft | B9: =Inputs!E9 | C9: =Inputs!F9 | D9: =Inputs!G9 | E9: =Inputs!H9 | F9: =Inputs!H9/Inputs!E9
A10: Amazon | B10: =Inputs!E10 | C10: =Inputs!F10 | D10: =Inputs!G10 | E10: =Inputs!H10 | F10: =Inputs!H10/Inputs!E10
A11: Netflix | B11: =Inputs!E11 | C11: =Inputs!F11 | D11: =Inputs!G11 | E11: =Inputs!H11 | F11: =Inputs!H11/Inputs!E11
A12: The Trade Desk | B12: =Inputs!E12 | C12: =Inputs!F12 | D12: =Inputs!G12 | E12: =Inputs!H12 | F12: =Inputs!H12/Inputs!E12
A13: Reddit | B13: =Inputs!E13 | C13: =Inputs!F13 | D13: =Inputs!G13 | E13: =Inputs!H13 | F13: =Inputs!H13/Inputs!E13
A15: Maximum | C15: =MAX(C8:C11) | D15: =MAX(D8:D11) | F15: =MAX(F8:F11)
A16: 75th Percentile | C16: =QUARTILE(C8:C11,3) | D16: =QUARTILE(D8:D11,3) | F16: =QUARTILE(F8:F11,3)
A17: Median | C17: =MEDIAN(C8:C11) | D17: =MEDIAN(D8:D11) | F17: =MEDIAN(F8:F11)
A18: 25th Percentile | C18: =QUARTILE(C8:C11,1) | D18: =QUARTILE(D8:D11,1) | F18: =QUARTILE(F8:F11,1)
A19: Minimum | C19: =MIN(C8:C11) | D19: =MIN(D8:D11) | F19: =MIN(F8:F11)

Sheet Valuation
A1: VALUATION MULTIPLES
A2: EV = Mkt Cap + Net Debt (negative net debt = net cash subtracts from EV). NM if EBITDA/NI <= 0.
A6: Company | B6: Mkt Cap | C6: EV | D6: EV / Rev | E6: EV / EBITDA | F6: P/E (TTM) | G6: Fwd P/E | H6: Comment
A7: Alphabet | B7: =Inputs!C7 | C7: =Inputs!C7+Inputs!D7 | D7: =(Inputs!C7+Inputs!D7)/Inputs!E7 | E7: =IF(Inputs!H7>0,(Inputs!C7+Inputs!D7)/Inputs!H7,"NM") | F7: =IF(Inputs!I7>0,Inputs!C7/Inputs!I7,"NM") | G7: =Inputs!J7 | H7: Target. Cheap on fwd P/E (~24x) vs the mega-cap median; DCF base $213 << $358 (FY26 capex spike).
A8: Meta Platforms | B8: =Inputs!C8 | C8: =Inputs!C8+Inputs!D8 | D8: =(Inputs!C8+Inputs!D8)/Inputs!E8 | E8: =IF(Inputs!H8>0,(Inputs!C8+Inputs!D8)/Inputs!H8,"NM") | F8: =IF(Inputs!I8>0,Inputs!C8/Inputs!I8,"NM") | G8: =Inputs!J8 | H8: Cheapest fwd P/E (~18x) in the mega-cap set; Reality Labs $4B/qtr drag.
A9: Microsoft | B9: =Inputs!C9 | C9: =Inputs!C9+Inputs!D9 | D9: =(Inputs!C9+Inputs!D9)/Inputs!E9 | E9: =IF(Inputs!H9>0,(Inputs!C9+Inputs!D9)/Inputs!H9,"NM") | F9: =IF(Inputs!I9>0,Inputs!C9/Inputs!I9,"NM") | G9: =Inputs!J9 | H9: Premium for Azure +40% + OpenAI exposure; $190B FY26 capex absorbs cash.
A10: Amazon | B10: =Inputs!C10 | C10: =Inputs!C10+Inputs!D10 | D10: =(Inputs!C10+Inputs!D10)/Inputs!E10 | E10: =IF(Inputs!H10>0,(Inputs!C10+Inputs!D10)/Inputs!H10,"NM") | F10: =IF(Inputs!I10>0,Inputs!C10/Inputs!I10,"NM") | G10: =Inputs!J10 | H10: Highest fwd P/E (~30x); AWS +28% reaccel + ads $70B+ TTM; retail margin still thin.
A11: Netflix | B11: =Inputs!C11 | C11: =Inputs!C11+Inputs!D11 | D11: =(Inputs!C11+Inputs!D11)/Inputs!E11 | E11: =IF(Inputs!H11>0,(Inputs!C11+Inputs!D11)/Inputs!H11,"NM") | F11: =IF(Inputs!I11>0,Inputs!C11/Inputs!I11,"NM") | G11: =Inputs!J11 | H11: Premium streaming P/E (~26x); subs no longer disclosed; ad business 2x in 2026.
A12: The Trade Desk | B12: =Inputs!C12 | C12: =Inputs!C12+Inputs!D12 | D12: =(Inputs!C12+Inputs!D12)/Inputs!E12 | E12: =IF(Inputs!H12>0,(Inputs!C12+Inputs!D12)/Inputs!H12,"NM") | F12: =IF(Inputs!I12>0,Inputs!C12/Inputs!I12,"NM") | G12: =Inputs!J12 | H12: Memo. Programmatic ad-tech; multiple compressed on deceleration to +12%.
A13: Reddit | B13: =Inputs!C13 | C13: =Inputs!C13+Inputs!D13 | D13: =(Inputs!C13+Inputs!D13)/Inputs!E13 | E13: =IF(Inputs!H13>0,(Inputs!C13+Inputs!D13)/Inputs!H13,"NM") | F13: =IF(Inputs!I13>0,Inputs!C13/Inputs!I13,"NM") | G13: =Inputs!J13 | H13: Memo. Hyper-growth (+69% rev) at ~50x P/E; data-licensing revenue accelerating.
A15: Maximum | D15: =MAX(D8:D11) | E15: =MAX(E8:E11) | F15: =MAX(F8:F11) | G15: =MAX(G8:G11)
A16: 75th Percentile | D16: =QUARTILE(D8:D11,3) | E16: =QUARTILE(E8:E11,3) | F16: =QUARTILE(F8:F11,3) | G16: =QUARTILE(G8:G11,3)
A17: Median | D17: =MEDIAN(D8:D11) | E17: =MEDIAN(E8:E11) | F17: =MEDIAN(F8:F11) | G17: =MEDIAN(G8:G11)
A18: 25th Percentile | D18: =QUARTILE(D8:D11,1) | E18: =QUARTILE(E8:E11,1) | F18: =QUARTILE(F8:F11,1) | G18: =QUARTILE(G8:G11,1)
A19: Minimum | D19: =MIN(D8:D11) | E19: =MIN(E8:E11) | F19: =MIN(F8:F11) | G19: =MIN(G8:G11)

Sheet Notes
A1: NOTES & CAVEATS
A3: Peer framing
A4: Mega-cap cohort (META, MSFT, AMZN, NFLX) is the main stat set — all platform-economy AI capex spenders.
A5: TTD and RDDT are ads-pure memo rows — useful frame for the Search/YouTube ad business, but too small for direct multiple read.
A6: GOOG is the target. Compare to mega-cap median on fwd P/E (cleanest cross-peer gauge).
A8: Data sources
A9: All Q1 CY2026 10-Qs / 8-Ks (Apr-May 2026) and FY25 10-Ks. Market data: StockAnalysis / companiesmarketcap / GuruFocus / Macrotrends.
A10: MCP terminals not configured. ENS aggregator figures vary 10-20% across sources (esp. TTM EBITDA definitions).
A12: Key adjustments / caveats
A13: MSFT TTM EBITDA implied from 17.1x EV/EBITDA (no direct disclosure).
A14: AMZN TTM NI inflated by Q1 $16.8B Anthropic mark-to-market gain.
A15: GOOG TTM NI similarly elevated by Anthropic-related fair-value changes.
... A17: Companion: GOOG-Model.xlsx (intrinsic DCF: base $213/share vs $358 market).
