Workbook

Sheet Drivers
A1: WALMART (WMT) — INTEGRATED MODEL: DRIVERS & ASSUMPTIONS
A2: As of June 3, 2026 | $ in millions | Blue = input/assumption, Black = formula | WMT FY ends ~Jan 31 (FY26 ended Jan 2026)
A4: SEGMENT REVENUE BUILD ($M)
A5: ($ in millions) | C5: FY2024A | D5: FY2025A | E5: FY2026A | F5: FY2027E | G5: FY2028E | H5: FY2029E | I5: FY2030E | J5: FY2031E
A6: Walmart US | C6: 442000 | D6: 462000 | E6: 485000 | F6: 509000 | G6: 535000 | H6: 562000 | I6: 590000 | J6: 619000
A7: Walmart International | C7: 101000 | D7: 115000 | E7: 122000 | F7: 131000 | G7: 141000 | H7: 152000 | I7: 163000 | J7: 175000
A8: Sam's Club | C8: 86000 | D8: 90000 | E8: 95000 | F8: 100000 | G8: 106000 | H8: 112000 | I8: 119000 | J8: 126000
A9: Total revenue | C9: =SUM(C6:C8) | D9: =SUM(D6:D8) | E9: =SUM(E6:E8) | F9: =SUM(F6:F8) | G9: =SUM(G6:G8) | H9: =SUM(H6:H8) | I9: =SUM(I6:I8) | J9: =SUM(J6:J8)
A10: Total revenue growth % | C10: n/a | D10: =D9/C9-1 | E10: =E9/D9-1 | F10: =F9/E9-1 | G10: =G9/F9-1 | H10: =H9/G9-1 | I10: =I9/H9-1 | J10: =J9/I9-1
A12: HIGH-MARGIN MIX TIER (Walmart Connect ads + membership)
A13: ($ in millions) | C13: FY2024A | D13: FY2025A | E13: FY2026A | F13: FY2027E | G13: FY2028E | H13: FY2029E | I13: FY2030E | J13: FY2031E
A14: Walmart Connect ad revenue ($M) | C14: 3200 | D14: 4200 | E14: 5500 | F14: 7000 | G14: 8800 | H14: 10800 | I14: 13000 | J14: 15500
A15: Membership revenue (Sam's + Walmart+, $M) | C15: 2600 | D15: 2900 | E15: 3300 | F15: 3700 | G15: 4100 | H15: 4500 | I15: 5000 | J15: 5500
A17: MARGIN & FREE-CASH-FLOW DRIVERS
A18: ($ in millions) | C18: FY2024A | D18: FY2025A | E18: FY2026A | F18: FY2027E | G18: FY2028E | H18: FY2029E | I18: FY2030E | J18: FY2031E
A19: Operating margin % (GAAP EBIT) | C19: 0.042 | D19: 0.044 | E19: 0.045 | F19: 0.047 | G19: 0.049 | H19: 0.051 | I19: 0.052 | J19: 0.053
A20: D&A % of revenue | C20: 0.018 | D20: 0.018 | E20: 0.018 | F20: 0.018 | G20: 0.018 | H20: 0.018 | I20: 0.018 | J20: 0.018
A21: Capex % of revenue | C21: 0.03 | D21: 0.03 | E21: 0.028 | F21: 0.027 | G21: 0.026 | H21: 0.025 | I21: 0.024 | J21: 0.024
A22: Cash tax rate % | C22: 0.245 | D22: 0.245 | E22: 0.245 | F22: 0.245 | G22: 0.245 | H22: 0.245 | I22: 0.245 | J22: 0.245
A23: Incr. NWC % of revenue growth | C23: 0 | D23: 0 | E23: 0 | F23: 0 | G23: 0 | H23: 0 | I23: 0 | J23: 0
A25: MARKET DATA & WACC INPUTS
A26: Current share price ($) | C26: 95.5
A27: Diluted shares (M) | C27: 8050
A28: Total debt ($M) | C28: 60000
A29: Cash & equivalents ($M) | C29: 11000
A30: Risk-free rate % | C30: 0.043
A31: Equity risk premium % | C31: 0.05
A32: Beta | C32: 0.6
A33: Pre-tax cost of debt % | C33: 0.045
A34: Terminal growth rate % | C34: 0.025
A36: WACC (computed)
A37: Cost of equity | C37: =C30+C32*C31
A38: After-tax cost of debt | C38: =C33*(1-E22)
A39: Market value of equity ($M) | C39: =C26*C27
A40: Net debt ($M) | C40: =C28-C29
A41: Equity weight | C41: =C39/(C39+C28)
A42: Debt weight | C42: =C28/(C39+C28)
A43: WACC | C43: =C41*C37+C42*C38

Sheet Income Statement
A1: INCOME STATEMENT ($M)
A4: ($ in millions) | C4: FY2024A | D4: FY2025A | E4: FY2026A | F4: FY2027E | G4: FY2028E | H4: FY2029E | I4: FY2030E | J4: FY2031E
A5: Total revenue | C5: =Drivers!C9 | D5: =Drivers!D9 | E5: =Drivers!E9 | F5: =Drivers!F9 | G5: =Drivers!G9 | H5: =Drivers!H9 | I5: =Drivers!I9 | J5: =Drivers!J9
A7: Operating income (EBIT) | C7: =Drivers!C19*C5 | D7: =Drivers!D19*D5 | E7: =Drivers!E19*E5 | F7: =Drivers!F19*F5 | G7: =Drivers!G19*G5 | H7: =Drivers!H19*H5 | I7: =Drivers!I19*I5 | J7: =Drivers!J19*J5
A8: (+) D&A | C8: =Drivers!C20*C5 | D8: =Drivers!D20*D5 | E8: =Drivers!E20*E5 | F8: =Drivers!F20*F5 | G8: =Drivers!G20*G5 | H8: =Drivers!H20*H5 | I8: =Drivers!I20*I5 | J8: =Drivers!J20*J5
A9: EBITDA | C9: =C7+C8 | D9: =D7+D8 | E9: =E7+E8 | F9: =F7+F8 | G9: =G7+G8 | H9: =H7+H8 | I9: =I7+I8 | J9: =J7+J8
A10: (-) Net interest expense | C10: 2500 | D10: 2350 | E10: 2300 | F10: =AVERAGE('Balance Sheet'!F7,'Balance Sheet'!E7)*Drivers!C33 | G10: =AVERAGE('Balance Sheet'!G7,'Balance Sheet'!F7)*Drivers!C33 | H10: =AVERAGE('Balance Sheet'!H7,'Balance Sheet'!G7)*Drivers!C33 | I10: =AVERAGE('Balance Sheet'!I7,'Balance Sheet'!H7)*Drivers!C33 | J10: =AVERAGE('Balance Sheet'!J7,'Balance Sheet'!I7)*Drivers!C33
A11: Pre-tax income | C11: =C9-C8-C10 | D11: =D9-D8-D10 | E11: =E9-E8-E10 | F11: =F9-F8-F10 | G11: =G9-G8-G10 | H11: =H9-H8-H10 | I11: =I9-I8-I10 | J11: =J9-J8-J10
A12: (-) Income taxes | C12: =C11*Drivers!C22 | D12: =D11*Drivers!D22 | E12: =E11*Drivers!E22 | F12: =F11*Drivers!F22 | G12: =G11*Drivers!G22 | H12: =H11*Drivers!H22 | I12: =I11*Drivers!I22 | J12: =J11*Drivers!J22
A13: Net income (GAAP) | C13: =C11-C12 | D13: =D11-D12 | E13: =E11-E12 | F13: =F11-F12 | G13: =G11-G12 | H13: =H11-H12 | I13: =I11-I12 | J13: =J11-J12
A14: Net margin % | C14: =C13/C5 | D14: =D13/D5 | E14: =E13/E5 | F14: =F13/F5 | G14: =G13/G5 | H14: =H13/H5 | I14: =I13/I5 | J14: =J13/J5

Sheet Balance Sheet
A1: BALANCE SHEET (summary, $M)
A4: ($ in millions) | C4: FY2024A | D4: FY2025A | E4: FY2026A | F4: FY2027E | G4: FY2028E | H4: FY2029E | I4: FY2030E | J4: FY2031E
A5: Cash & equivalents | C5: 9000 | D5: 9900 | E5: 11000 | F5: =E5+'Cash Flow'!F13-F10-F11 | G5: =F5+'Cash Flow'!G13-G10-G11 | H5: =G5+'Cash Flow'!H13-H10-H11 | I5: =H5+'Cash Flow'!I13-I10-I11 | J5: =I5+'Cash Flow'!J13-J10-J11
A6: Other assets (plug) | C6: =C7+C8-C5 | D6: =D7+D8-D5 | E6: =E7+E8-E5 | F6: =F7+F8-F5 | G6: =G7+G8-G5 | H6: =H7+H8-H5 | I6: =I7+I8-I5 | J6: =J7+J8-J5
A7: Total debt | C7: 60000 | D7: 61000 | E7: 60000 | F7: =E7-F10 | G7: =F7-G10 | H7: =G7-H10 | I7: =H7-I10 | J7: =I7-J10
A8: Shareholders' equity | C8: 83861 | D8: 91013 | E8: 95000 | F8: =E8+'Income Statement'!F13-F11 | G8: =F8+'Income Statement'!G13-G11 | H8: =G8+'Income Statement'!H13-H11 | I8: =H8+'Income Statement'!I13-I11 | J8: =I8+'Income Statement'!J13-J11
A9: Net debt | C9: =C7-C5 | D9: =D7-D5 | E9: =E7-E5 | F9: =F7-F5 | G9: =G7-G5 | H9: =H7-H5 | I9: =I7-I5 | J9: =J7-J5
A10: Debt repayment (in year) | F10: 2000 | G10: 2000 | H10: 2000 | I10: 1500 | J10: 1500
A11: Dividends + buybacks | F11: 15000 | G11: 16000 | H11: 17500 | I11: 19000 | J11: 20500

Sheet Cash Flow
A1: CASH FLOW & FREE CASH FLOW ($M)
A4: ($ in millions) | C4: FY2024A | D4: FY2025A | E4: FY2026A | F4: FY2027E | G4: FY2028E | H4: FY2029E | I4: FY2030E | J4: FY2031E
A5: EBIT | C5: ='Income Statement'!C7 | D5: ='Income Statement'!D7 | E5: ='Income Statement'!E7 | F5: ='Income Statement'!F7 | G5: ='Income Statement'!G7 | H5: ='Income Statement'!H7 | I5: ='Income Statement'!I7 | J5: ='Income Statement'!J7
A6: (-) Cash taxes on EBIT | C6: =C5*Drivers!C22 | D6: =D5*Drivers!D22 | E6: =E5*Drivers!E22 | F6: =F5*Drivers!F22 | G6: =G5*Drivers!G22 | H6: =H5*Drivers!H22 | I6: =I5*Drivers!I22 | J6: =J5*Drivers!J22
A7: NOPAT | C7: =C5-C6 | D7: =D5-D6 | E7: =E5-E6 | F7: =F5-F6 | G7: =G5-G6 | H7: =H5-H6 | I7: =I5-I6 | J7: =J5-J6
A8: (+) D&A | C8: ='Income Statement'!C8 | D8: ='Income Statement'!D8 | E8: ='Income Statement'!E8 | F8: ='Income Statement'!F8 | G8: ='Income Statement'!G8 | H8: ='Income Statement'!H8 | I8: ='Income Statement'!I8 | J8: ='Income Statement'!J8
A9: (-) Capex | C9: =Drivers!C21*Drivers!C9 | D9: =Drivers!D21*Drivers!D9 | E9: =Drivers!E21*Drivers!E9 | F9: =Drivers!F21*Drivers!F9 | G9: =Drivers!G21*Drivers!G9 | H9: =Drivers!H21*Drivers!H9 | I9: =Drivers!I21*Drivers!I9 | J9: =Drivers!J21*Drivers!J9
A10: (-) Increase in net working capital | C10: =0 | D10: =(Drivers!D9-Drivers!C9)*Drivers!D23 | E10: =(Drivers!E9-Drivers!D9)*Drivers!E23 | F10: =(Drivers!F9-Drivers!E9)*Drivers!F23 | G10: =(Drivers!G9-Drivers!F9)*Drivers!G23 | H10: =(Drivers!H9-Drivers!G9)*Drivers!H23 | I10: =(Drivers!I9-Drivers!H9)*Drivers!I23 | J10: =(Drivers!J9-Drivers!I9)*Drivers!J23
A11: Unlevered free cash flow | C11: =C7+C8-C9-C10 | D11: =D7+D8-D9-D10 | E11: =E7+E8-E9-E10 | F11: =F7+F8-F9-F10 | G11: =G7+G8-G9-G10 | H11: =H7+H8-H9-H10 | I11: =I7+I8-I9-I10 | J11: =J7+J8-J9-J10
A12: (-) After-tax net interest | C12: ='Income Statement'!C10*(1-Drivers!C22) | D12: ='Income Statement'!D10*(1-Drivers!D22) | E12: ='Income Statement'!E10*(1-Drivers!E22) | F12: ='Income Statement'!F10*(1-Drivers!F22) | G12: ='Income Statement'!G10*(1-Drivers!G22) | H12: ='Income Statement'!H10*(1-Drivers!H22) | I12: ='Income Statement'!I10*(1-Drivers!I22) | J12: ='Income Statement'!J10*(1-Drivers!J22)
A13: Levered free cash flow | C13: =C11-C12 | D13: =D11-D12 | E13: =E11-E12 | F13: =F11-F12 | G13: =G11-G12 | H13: =H11-H12 | I13: =I11-I12 | J13: =J11-J12
A14: Unlevered FCF margin % | C14: =C11/Drivers!C9 | D14: =D11/Drivers!D9 | E14: =E11/Drivers!E9 | F14: =F11/Drivers!F9 | G14: =G11/Drivers!G9 | H14: =H11/Drivers!H9 | I14: =I11/Drivers!I9 | J14: =J11/Drivers!J9

Sheet DCF
A1: DISCOUNTED CASH FLOW VALUATION
A4: Projection year | B4: FY2027E | C4: FY2028E | D4: FY2029E | E4: FY2030E | F4: FY2031E
A5: Period (n) | B5: =1 | C5: =2 | D5: =3 | E5: =4 | F5: =5
A6: Unlevered FCF | B6: ='Cash Flow'!F11 | C6: ='Cash Flow'!G11 | D6: ='Cash Flow'!H11 | E6: ='Cash Flow'!I11 | F6: ='Cash Flow'!J11
A7: Discount factor @ WACC | B7: =1/(1+Drivers!C43)^B5 | C7: =1/(1+Drivers!C43)^C5 | D7: =1/(1+Drivers!C43)^D5 | E7: =1/(1+Drivers!C43)^E5 | F7: =1/(1+Drivers!C43)^F5
A8: PV of unlevered FCF | B8: =B6*B7 | C8: =C6*C7 | D8: =D6*D7 | E8: =E6*E7 | F8: =F6*F7
A10: Sum of PV of explicit FCF (FY27-31) | C10: =SUM(B8:F8)
A11: Terminal-year FCF (FY2031) | C11: =F6
A12: Terminal value (Gordon) | C12: =F6*(1+Drivers!C34)/(Drivers!C43-Drivers!C34)
A13: PV of terminal value | C13: =C12*F7
A14: Enterprise value | C14: =C10+C13
A15: (-) Net debt | C15: =Drivers!C28-Drivers!C29
A16: Equity value | C16: =C14-C15
A17: Diluted shares (M) | C17: =Drivers!C27
A18: Implied value per share ($) | C18: =C16/C17
A19: Current share price ($) | C19: =Drivers!C26
A20: Upside / (downside) to current | C20: =C18/C19-1
A21: TV as % of enterprise value | C21: =C13/C14
A22: SENSITIVITY — Implied $/share: WACC (down) x Terminal growth (across)
B23: Terminal g → | C23: 0.015 | D23: 0.02 | E23: 0.025 | F23: 0.03 | G23: 0.035
A24: WACC ↓ | B24: 0.06 | C24: =(($B$6/(1+$B$24)^1+$C$6/(1+$B$24)^2+$D$6/(1+$B$24)^3+$E$6/(1+$B$24)^4+$F$6/(1+$B$24)^5)+(($F$6*(1+C$23)/($B$24-C$23))/(1+$B$24)^5)-Drivers!$C$28+Drivers!$C$29)/Drivers!$C$27 | D24: =(($B$6/(1+$B$24)^1+$C$6/(1+$B$24)^2+$D$6/(1+$B$24)^3+$E$6/(1+$B$24)^4+$F$6/(1+$B$24)^5)+(($F$6*(1+D$23)/($B$24-D$23))/(1+$B$24)^5)-Drivers!$C$28+Drivers!$C$29)/Drivers!$C$27 | E24: =(($B$6/(1+$B$24)^1+$C$6/(1+$B$24)^2+$D$6/(1+$B$24)^3+$E$6/(1+$B$24)^4+$F$6/(1+$B$24)^5)+(($F$6*(1+E$23)/($B$24-E$23))/(1+$B$24)^5)-Drivers!$C$28+Drivers!$C$29)/Drivers!$C$27 | F24: =(($B$6/(1+$B$24)^1+$C$6/(1+$B$24)^2+$D$6/(1+$B$24)^3+$E$6/(1+$B$24)^4+$F$6/(1+$B$24)^5)+(($F$6*(1+F$23)/($B$24-F$23))/(1+$B$24)^5)-Drivers!$C$28+Drivers!$C$29)/Drivers!$C$27 | G24: =(($B$6/(1+$B$24)^1+$C$6/(1+$B$24)^2+$D$6/(1+$B$24)^3+$E$6/(1+$B$24)^4+$F$6/(1+$B$24)^5)+(($F$6*(1+G$23)/($B$24-G$23))/(1+$B$24)^5)-Drivers!$C$28+Drivers!$C$29)/Drivers!$C$27
B25: 0.065 | C25: =(($B$6/(1+$B$25)^1+$C$6/(1+$B$25)^2+$D$6/(1+$B$25)^3+$E$6/(1+$B$25)^4+$F$6/(1+$B$25)^5)+(($F$6*(1+C$23)/($B$25-C$23))/(1+$B$25)^5)-Drivers!$C$28+Drivers!$C$29)/Drivers!$C$27 | D25: =(($B$6/(1+$B$25)^1+$C$6/(1+$B$25)^2+$D$6/(1+$B$25)^3+$E$6/(1+$B$25)^4+$F$6/(1+$B$25)^5)+(($F$6*(1+D$23)/($B$25-D$23))/(1+$B$25)^5)-Drivers!$C$28+Drivers!$C$29)/Drivers!$C$27 | E25: =(($B$6/(1+$B$25)^1+$C$6/(1+$B$25)^2+$D$6/(1+$B$25)^3+$E$6/(1+$B$25)^4+$F$6/(1+$B$25)^5)+(($F$6*(1+E$23)/($B$25-E$23))/(1+$B$25)^5)-Drivers!$C$28+Drivers!$C$29)/Drivers!$C$27 | F25: =(($B$6/(1+$B$25)^1+$C$6/(1+$B$25)^2+$D$6/(1+$B$25)^3+$E$6/(1+$B$25)^4+$F$6/(1+$B$25)^5)+(($F$6*(1+F$23)/($B$25-F$23))/(1+$B$25)^5)-Drivers!$C$28+Drivers!$C$29)/Drivers!$C$27 | G25: =(($B$6/(1+$B$25)^1+$C$6/(1+$B$25)^2+$D$6/(1+$B$25)^3+$E$6/(1+$B$25)^4+$F$6/(1+$B$25)^5)+(($F$6*(1+G$23)/($B$25-G$23))/(1+$B$25)^5)-Drivers!$C$28+Drivers!$C$29)/Drivers!$C$27
B26: 0.07 | C26: =(($B$6/(1+$B$26)^1+$C$6/(1+$B$26)^2+$D$6/(1+$B$26)^3+$E$6/(1+$B$26)^4+$F$6/(1+$B$26)^5)+(($F$6*(1+C$23)/($B$26-C$23))/(1+$B$26)^5)-Drivers!$C$28+Drivers!$C$29)/Drivers!$C$27 | D26: =(($B$6/(1+$B$26)^1+$C$6/(1+$B$26)^2+$D$6/(1+$B$26)^3+$E$6/(1+$B$26)^4+$F$6/(1+$B$26)^5)+(($F$6*(1+D$23)/($B$26-D$23))/(1+$B$26)^5)-Drivers!$C$28+Drivers!$C$29)/Drivers!$C$27 | E26: =(($B$6/(1+$B$26)^1+$C$6/(1+$B$26)^2+$D$6/(1+$B$26)^3+$E$6/(1+$B$26)^4+$F$6/(1+$B$26)^5)+(($F$6*(1+E$23)/($B$26-E$23))/(1+$B$26)^5)-Drivers!$C$28+Drivers!$C$29)/Drivers!$C$27 | F26: =(($B$6/(1+$B$26)^1+$C$6/(1+$B$26)^2+$D$6/(1+$B$26)^3+$E$6/(1+$B$26)^4+$F$6/(1+$B$26)^5)+(($F$6*(1+F$23)/($B$26-F$23))/(1+$B$26)^5)-Drivers!$C$28+Drivers!$C$29)/Drivers!$C$27 | G26: =(($B$6/(1+$B$26)^1+$C$6/(1+$B$26)^2+$D$6/(1+$B$26)^3+$E$6/(1+$B$26)^4+$F$6/(1+$B$26)^5)+(($F$6*(1+G$23)/($B$26-G$23))/(1+$B$26)^5)-Drivers!$C$28+Drivers!$C$29)/Drivers!$C$27
B27: 0.075 | C27: =(($B$6/(1+$B$27)^1+$C$6/(1+$B$27)^2+$D$6/(1+$B$27)^3+$E$6/(1+$B$27)^4+$F$6/(1+$B$27)^5)+(($F$6*(1+C$23)/($B$27-C$23))/(1+$B$27)^5)-Drivers!$C$28+Drivers!$C$29)/Drivers!$C$27 | D27: =(($B$6/(1+$B$27)^1+$C$6/(1+$B$27)^2+$D$6/(1+$B$27)^3+$E$6/(1+$B$27)^4+$F$6/(1+$B$27)^5)+(($F$6*(1+D$23)/($B$27-D$23))/(1+$B$27)^5)-Drivers!$C$28+Drivers!$C$29)/Drivers!$C$27 | E27: =(($B$6/(1+$B$27)^1+$C$6/(1+$B$27)^2+$D$6/(1+$B$27)^3+$E$6/(1+$B$27)^4+$F$6/(1+$B$27)^5)+(($F$6*(1+E$23)/($B$27-E$23))/(1+$B$27)^5)-Drivers!$C$28+Drivers!$C$29)/Drivers!$C$27 | F27: =(($B$6/(1+$B$27)^1+$C$6/(1+$B$27)^2+$D$6/(1+$B$27)^3+$E$6/(1+$B$27)^4+$F$6/(1+$B$27)^5)+(($F$6*(1+F$23)/($B$27-F$23))/(1+$B$27)^5)-Drivers!$C$28+Drivers!$C$29)/Drivers!$C$27 | G27: =(($B$6/(1+$B$27)^1+$C$6/(1+$B$27)^2+$D$6/(1+$B$27)^3+$E$6/(1+$B$27)^4+$F$6/(1+$B$27)^5)+(($F$6*(1+G$23)/($B$27-G$23))/(1+$B$27)^5)-Drivers!$C$28+Drivers!$C$29)/Drivers!$C$27
B28: 0.08 | C28: =(($B$6/(1+$B$28)^1+$C$6/(1+$B$28)^2+$D$6/(1+$B$28)^3+$E$6/(1+$B$28)^4+$F$6/(1+$B$28)^5)+(($F$6*(1+C$23)/($B$28-C$23))/(1+$B$28)^5)-Drivers!$C$28+Drivers!$C$29)/Drivers!$C$27 | D28: =(($B$6/(1+$B$28)^1+$C$6/(1+$B$28)^2+$D$6/(1+$B$28)^3+$E$6/(1+$B$28)^4+$F$6/(1+$B$28)^5)+(($F$6*(1+D$23)/($B$28-D$23))/(1+$B$28)^5)-Drivers!$C$28+Drivers!$C$29)/Drivers!$C$27 | E28: =(($B$6/(1+$B$28)^1+$C$6/(1+$B$28)^2+$D$6/(1+$B$28)^3+$E$6/(1+$B$28)^4+$F$6/(1+$B$28)^5)+(($F$6*(1+E$23)/($B$28-E$23))/(1+$B$28)^5)-Drivers!$C$28+Drivers!$C$29)/Drivers!$C$27 | F28: =(($B$6/(1+$B$28)^1+$C$6/(1+$B$28)^2+$D$6/(1+$B$28)^3+$E$6/(1+$B$28)^4+$F$6/(1+$B$28)^5)+(($F$6*(1+F$23)/($B$28-F$23))/(1+$B$28)^5)-Drivers!$C$28+Drivers!$C$29)/Drivers!$C$27 | G28: =(($B$6/(1+$B$28)^1+$C$6/(1+$B$28)^2+$D$6/(1+$B$28)^3+$E$6/(1+$B$28)^4+$F$6/(1+$B$28)^5)+(($F$6*(1+G$23)/($B$28-G$23))/(1+$B$28)^5)-Drivers!$C$28+Drivers!$C$29)/Drivers!$C$27
A30: Center cell (WACC 7.0% / g 2.5%) = base case; cross-check vs C18 implied per share.

Sheet Notes
A1: WMT MODEL — METHODOLOGY & CAVEATS
A3: Methodology
A4: Integrated 3-statement model (IS/BS/CF) feeding an unlevered DCF. Drivers tab drives everything.
A5: Revenue built bottom-up: Walmart US + Walmart International + Sam's Club.
A6: Separate visibility on the WMT thesis margin lever: Walmart Connect ad revenue + membership.
A7: DCF: 5-year explicit FCF (FY27-31) + Gordon terminal value; net debt deducted to get equity.
A9: Base case stance
A10: WMT US +5%/yr (sustained comp +3-4% + new units); Intl +7-8% (Flipkart, Walmex); Sam's +5-6%.
A11: EBIT margin expands 4.5% (FY26) -> 5.3% (FY31) as ad+marketplace+membership mix lifts margin.
A12: Walmart Connect ramps ~$5.5B (FY26) -> ~$15.5B (FY31) at ~40% EBIT margin per mgmt.
A13: Lower WACC (~7%) and terminal growth (2.5%) than AVGO — defensive consumer-staple profile.
A15: Data sources & caveats
... A20: Research / decision-framing only — NOT investment advice.
