Workbook

Sheet Drivers
A1: BROADCOM (AVGO) — INTEGRATED MODEL: DRIVERS & ASSUMPTIONS
A2: As of June 3, 2026 (post-Q2 FY26 print) | $ in millions unless noted | Blue = input/assumption (see cell comments), Black = formula
A4: SEGMENT REVENUE BUILD ($M)
A5: ($ in millions) | C5: FY2023A | D5: FY2024A | E5: FY2025A | F5: FY2026E | G5: FY2027E | H5: FY2028E | I5: FY2029E | J5: FY2030E
A6: AI Semiconductor revenue | C6: 4200 | D6: 12200 | E6: 20000 | F6: 50000 | G6: 85000 | H6: 108000 | I6: 128000 | J6: 145000
A7: Non-AI Semiconductor revenue | C7: 24015 | D7: 17896 | E7: 17400 | F7: 17500 | G7: 18500 | H7: 19500 | I7: 20500 | J7: 21500
A8: Infrastructure Software revenue | C8: 7604 | D8: 21478 | E8: 26487 | F8: 28000 | G8: 30000 | H8: 32000 | I8: 34000 | J8: 36000
A9: Total revenue | C9: =SUM(C6:C8) | D9: =SUM(D6:D8) | E9: =SUM(E6:E8) | F9: =SUM(F6:F8) | G9: =SUM(G6:G8) | H9: =SUM(H6:H8) | I9: =SUM(I6:I8) | J9: =SUM(J6:J8)
A10: Total revenue growth % | C10: n/a | D10: =D9/C9-1 | E10: =E9/D9-1 | F10: =F9/E9-1 | G10: =G9/F9-1 | H10: =H9/G9-1 | I10: =I9/H9-1 | J10: =J9/I9-1
A11: AI % of total revenue | C11: =C6/C9 | D11: =D6/D9 | E11: =E6/E9 | F11: =F6/F9 | G11: =G6/G9 | H11: =H6/H9 | I11: =I6/I9 | J11: =J6/J9
A13: MARGIN & FREE-CASH-FLOW DRIVERS
A14: ($ in millions) | C14: FY2023A | D14: FY2024A | E14: FY2025A | F14: FY2026E | G14: FY2027E | H14: FY2028E | I14: FY2029E | J14: FY2030E
A15: Operating margin % (GAAP, EBIT) | C15: 0.46 | D15: 0.26 | E15: 0.4 | F15: 0.44 | G15: 0.47 | H15: 0.49 | I15: 0.5 | J15: 0.51
A16: D&A % of revenue | C16: 0.18 | D16: 0.22 | E16: 0.16 | F16: 0.12 | G16: 0.1 | H16: 0.08 | I16: 0.07 | J16: 0.06
A17: Capex % of revenue | C17: 0.014 | D17: 0.005 | E17: 0.02 | F17: 0.025 | G17: 0.025 | H17: 0.025 | I17: 0.025 | J17: 0.025
A18: Cash tax rate % | C18: 0.14 | D18: 0.14 | E18: 0.14 | F18: 0.14 | G18: 0.14 | H18: 0.14 | I18: 0.15 | J18: 0.15
A19: Incr. NWC % of revenue growth | C19: 0.03 | D19: 0.03 | E19: 0.03 | F19: 0.03 | G19: 0.03 | H19: 0.03 | I19: 0.03 | J19: 0.03
A21: MARKET DATA & WACC INPUTS
A22: Current share price ($) | C22: 481.62
A23: Diluted shares (M) | C23: 4730
A24: Total debt ($M) | C24: 65000
A25: Cash & equivalents ($M) | C25: 16000
A26: Risk-free rate % | C26: 0.043
A27: Equity risk premium % | C27: 0.05
A28: Beta | C28: 1.072
A29: Pre-tax cost of debt % | C29: 0.05
A30: Terminal growth rate % | C30: 0.035
A32: WACC (computed)
A33: Cost of equity | C33: =C26+C28*C27
A34: After-tax cost of debt | C34: =C29*(1-E18)
A35: Market value of equity ($M) | C35: =C22*C23
A36: Net debt ($M) | C36: =C24-C25
A37: Equity weight | C37: =C35/(C35+C24)
A38: Debt weight | C38: =C24/(C35+C24)
A39: WACC | C39: =C37*C33+C38*C34

Sheet Income Statement
A1: INCOME STATEMENT ($M)
A2: Revenue & margins driven from Drivers tab. GAAP basis; large D&A reflects acquired-intangible amortization.
A4: ($ in millions) | C4: FY2023A | D4: FY2024A | E4: FY2025A | F4: FY2026E | G4: FY2027E | H4: FY2028E | I4: FY2029E | J4: FY2030E
A5: Total revenue | C5: =Drivers!C9 | D5: =Drivers!D9 | E5: =Drivers!E9 | F5: =Drivers!F9 | G5: =Drivers!G9 | H5: =Drivers!H9 | I5: =Drivers!I9 | J5: =Drivers!J9
A7: Operating income (EBIT) | C7: =Drivers!C15*C5 | D7: =Drivers!D15*D5 | E7: =Drivers!E15*E5 | F7: =Drivers!F15*F5 | G7: =Drivers!G15*G5 | H7: =Drivers!H15*H5 | I7: =Drivers!I15*I5 | J7: =Drivers!J15*J5
A8: (+) Depreciation & amortization | C8: =Drivers!C16*C5 | D8: =Drivers!D16*D5 | E8: =Drivers!E16*E5 | F8: =Drivers!F16*F5 | G8: =Drivers!G16*G5 | H8: =Drivers!H16*H5 | I8: =Drivers!I16*I5 | J8: =Drivers!J16*J5
A9: EBITDA | C9: =C7+C8 | D9: =D7+D8 | E9: =E7+E8 | F9: =F7+F8 | G9: =G7+G8 | H9: =H7+H8 | I9: =I7+I8 | J9: =J7+J8
A10: (-) Net interest expense | C10: 1622 | D10: 3598 | E10: 3500 | F10: =AVERAGE('Balance Sheet'!F7,'Balance Sheet'!E7)*Drivers!C29 | G10: =AVERAGE('Balance Sheet'!G7,'Balance Sheet'!F7)*Drivers!C29 | H10: =AVERAGE('Balance Sheet'!H7,'Balance Sheet'!G7)*Drivers!C29 | I10: =AVERAGE('Balance Sheet'!I7,'Balance Sheet'!H7)*Drivers!C29 | J10: =AVERAGE('Balance Sheet'!J7,'Balance Sheet'!I7)*Drivers!C29
A11: Pre-tax income | C11: =C9-C8-C10 | D11: =D9-D8-D10 | E11: =E9-E8-E10 | F11: =F9-F8-F10 | G11: =G9-G8-G10 | H11: =H9-H8-H10 | I11: =I9-I8-I10 | J11: =J9-J8-J10
A12: (-) Income taxes | C12: =C11*Drivers!C18 | D12: =D11*Drivers!D18 | E12: =E11*Drivers!E18 | F12: =F11*Drivers!F18 | G12: =G11*Drivers!G18 | H12: =H11*Drivers!H18 | I12: =I11*Drivers!I18 | J12: =J11*Drivers!J18
A13: Net income (GAAP) | C13: =C11-C12 | D13: =D11-D12 | E13: =E11-E12 | F13: =F11-F12 | G13: =G11-G12 | H13: =H11-H12 | I13: =I11-I12 | J13: =J11-J12
A14: Net margin % | C14: =C13/C5 | D14: =D13/D5 | E14: =E13/E5 | F14: =F13/F5 | G14: =G13/G5 | H14: =H13/H5 | I14: =I13/I5 | J14: =J13/J5

Sheet Balance Sheet
A1: BALANCE SHEET (summary) ($M)
A2: Cash builds from levered FCF; debt amortizes on a schedule; equity rolls with NI less dividends & buybacks.
A4: ($ in millions) | C4: FY2023A | D4: FY2024A | E4: FY2025A | F4: FY2026E | G4: FY2027E | H4: FY2028E | I4: FY2029E | J4: FY2030E
A5: Cash & equivalents | C5: 14189 | D5: 9348 | E5: 10500 | F5: =E5+'Cash Flow'!F13-F10-F11 | G5: =F5+'Cash Flow'!G13-G10-G11 | H5: =G5+'Cash Flow'!H13-H10-H11 | I5: =H5+'Cash Flow'!I13-I10-I11 | J5: =I5+'Cash Flow'!J13-J10-J11
A6: Other assets (plug) | C6: =C7+C8-C5 | D6: =D7+D8-D5 | E6: =E7+E8-E5 | F6: =F7+F8-F5 | G6: =G7+G8-G5 | H6: =H7+H8-H5 | I6: =I7+I8-I5 | J6: =J7+J8-J5
A7: Total debt | C7: 39229 | D7: 69955 | E7: 67500 | F7: =E7-F10 | G7: =F7-G10 | H7: =G7-H10 | I7: =H7-I10 | J7: =I7-J10
A8: Shareholders' equity | C8: 49902 | D8: 67998 | E8: 70000 | F8: =E8+'Income Statement'!F13-F11 | G8: =F8+'Income Statement'!G13-G11 | H8: =G8+'Income Statement'!H13-H11 | I8: =H8+'Income Statement'!I13-I11 | J8: =I8+'Income Statement'!J13-J11
A9: Net debt | C9: =C7-C5 | D9: =D7-D5 | E9: =E7-E5 | F9: =F7-F5 | G9: =G7-G5 | H9: =H7-H5 | I9: =I7-I5 | J9: =J7-J5
A10: Debt repayment (in year) | F10: 6000 | G10: 6000 | H10: 5000 | I10: 4000 | J10: 3000
A11: Dividends + buybacks | F11: 14000 | G11: 16000 | H11: 18000 | I11: 20000 | J11: 22000

Sheet Cash Flow
A1: CASH FLOW & FREE CASH FLOW ($M)
A2: Unlevered FCF feeds the DCF. Levered FCF (after interest) feeds the Balance Sheet cash roll.
A4: ($ in millions) | C4: FY2023A | D4: FY2024A | E4: FY2025A | F4: FY2026E | G4: FY2027E | H4: FY2028E | I4: FY2029E | J4: FY2030E
A5: EBIT (operating income) | C5: ='Income Statement'!C7 | D5: ='Income Statement'!D7 | E5: ='Income Statement'!E7 | F5: ='Income Statement'!F7 | G5: ='Income Statement'!G7 | H5: ='Income Statement'!H7 | I5: ='Income Statement'!I7 | J5: ='Income Statement'!J7
A6: (-) Cash taxes on EBIT | C6: =C5*Drivers!C18 | D6: =D5*Drivers!D18 | E6: =E5*Drivers!E18 | F6: =F5*Drivers!F18 | G6: =G5*Drivers!G18 | H6: =H5*Drivers!H18 | I6: =I5*Drivers!I18 | J6: =J5*Drivers!J18
A7: NOPAT | C7: =C5-C6 | D7: =D5-D6 | E7: =E5-E6 | F7: =F5-F6 | G7: =G5-G6 | H7: =H5-H6 | I7: =I5-I6 | J7: =J5-J6
A8: (+) Depreciation & amortization | C8: ='Income Statement'!C8 | D8: ='Income Statement'!D8 | E8: ='Income Statement'!E8 | F8: ='Income Statement'!F8 | G8: ='Income Statement'!G8 | H8: ='Income Statement'!H8 | I8: ='Income Statement'!I8 | J8: ='Income Statement'!J8
A9: (-) Capex | C9: =Drivers!C17*Drivers!C9 | D9: =Drivers!D17*Drivers!D9 | E9: =Drivers!E17*Drivers!E9 | F9: =Drivers!F17*Drivers!F9 | G9: =Drivers!G17*Drivers!G9 | H9: =Drivers!H17*Drivers!H9 | I9: =Drivers!I17*Drivers!I9 | J9: =Drivers!J17*Drivers!J9
A10: (-) Increase in net working capital | C10: =0 | D10: =(D5/Drivers!D15-C5/Drivers!C15)*Drivers!D19 | E10: =(E5/Drivers!E15-D5/Drivers!D15)*Drivers!E19 | F10: =(F5/Drivers!F15-E5/Drivers!E15)*Drivers!F19 | G10: =(G5/Drivers!G15-F5/Drivers!F15)*Drivers!G19 | H10: =(H5/Drivers!H15-G5/Drivers!G15)*Drivers!H19 | I10: =(I5/Drivers!I15-H5/Drivers!H15)*Drivers!I19 | J10: =(J5/Drivers!J15-I5/Drivers!I15)*Drivers!J19
A11: Unlevered free cash flow | C11: =C7+C8-C9-C10 | D11: =D7+D8-D9-D10 | E11: =E7+E8-E9-E10 | F11: =F7+F8-F9-F10 | G11: =G7+G8-G9-G10 | H11: =H7+H8-H9-H10 | I11: =I7+I8-I9-I10 | J11: =J7+J8-J9-J10
A12: (-) After-tax net interest | C12: ='Income Statement'!C10*(1-Drivers!C18) | D12: ='Income Statement'!D10*(1-Drivers!D18) | E12: ='Income Statement'!E10*(1-Drivers!E18) | F12: ='Income Statement'!F10*(1-Drivers!F18) | G12: ='Income Statement'!G10*(1-Drivers!G18) | H12: ='Income Statement'!H10*(1-Drivers!H18) | I12: ='Income Statement'!I10*(1-Drivers!I18) | J12: ='Income Statement'!J10*(1-Drivers!J18)
A13: Levered free cash flow | C13: =C11-C12 | D13: =D11-D12 | E13: =E11-E12 | F13: =F11-F12 | G13: =G11-G12 | H13: =H11-H12 | I13: =I11-I12 | J13: =J11-J12
A14: Unlevered FCF margin % | C14: =C11/Drivers!C9 | D14: =D11/Drivers!D9 | E14: =E11/Drivers!E9 | F14: =F11/Drivers!F9 | G14: =G11/Drivers!G9 | H14: =H11/Drivers!H9 | I14: =I11/Drivers!I9 | J14: =J11/Drivers!J9

Sheet DCF
A1: DISCOUNTED CASH FLOW VALUATION
A2: Unlevered FCF (Cash Flow tab) discounted at WACC (Drivers). Terminal value via Gordon growth. $ in millions except per-share.
A4: Projection year | B4: FY2026E | C4: FY2027E | D4: FY2028E | E4: FY2029E | F4: FY2030E
A5: Period (n) | B5: =1 | C5: =2 | D5: =3 | E5: =4 | F5: =5
A6: Unlevered FCF | B6: ='Cash Flow'!F11 | C6: ='Cash Flow'!G11 | D6: ='Cash Flow'!H11 | E6: ='Cash Flow'!I11 | F6: ='Cash Flow'!J11
A7: Discount factor @ WACC | B7: =1/(1+Drivers!C39)^B5 | C7: =1/(1+Drivers!C39)^C5 | D7: =1/(1+Drivers!C39)^D5 | E7: =1/(1+Drivers!C39)^E5 | F7: =1/(1+Drivers!C39)^F5
A8: PV of unlevered FCF | B8: =B6*B7 | C8: =C6*C7 | D8: =D6*D7 | E8: =E6*E7 | F8: =F6*F7
A10: Sum of PV of explicit FCF (FY26-30) | C10: =SUM(B8:F8)
A11: Terminal-year FCF (FY2030) | C11: =F6
A12: Terminal value (Gordon growth) | C12: =F6*(1+Drivers!C30)/(Drivers!C39-Drivers!C30)
A13: PV of terminal value | C13: =C12*F7
A14: Enterprise value | C14: =C10+C13
A15: (-) Net debt | C15: =Drivers!C36
A16: Equity value | C16: =C14-C15
A17: Diluted shares (M) | C17: =Drivers!C23
A18: Implied value per share ($) | C18: =C16/C17
A19: Current share price ($) | C19: =Drivers!C22
A20: Upside / (downside) to current | C20: =C18/C19-1
A21: TV as % of enterprise value | C21: =C13/C14
A22: SENSITIVITY — Implied value per share ($): WACC (down) x Terminal growth (across)
B23: Terminal g → | C23: 0.025 | D23: 0.03 | E23: 0.035 | F23: 0.04 | G23: 0.045
A24: WACC ↓ | B24: 0.085 | C24: =(($B$6/(1+$B$24)^1+$C$6/(1+$B$24)^2+$D$6/(1+$B$24)^3+$E$6/(1+$B$24)^4+$F$6/(1+$B$24)^5)+(($F$6*(1+C$23)/($B$24-C$23))/(1+$B$24)^5)-Drivers!$C$36)/Drivers!$C$23 | D24: =(($B$6/(1+$B$24)^1+$C$6/(1+$B$24)^2+$D$6/(1+$B$24)^3+$E$6/(1+$B$24)^4+$F$6/(1+$B$24)^5)+(($F$6*(1+D$23)/($B$24-D$23))/(1+$B$24)^5)-Drivers!$C$36)/Drivers!$C$23 | E24: =(($B$6/(1+$B$24)^1+$C$6/(1+$B$24)^2+$D$6/(1+$B$24)^3+$E$6/(1+$B$24)^4+$F$6/(1+$B$24)^5)+(($F$6*(1+E$23)/($B$24-E$23))/(1+$B$24)^5)-Drivers!$C$36)/Drivers!$C$23 | F24: =(($B$6/(1+$B$24)^1+$C$6/(1+$B$24)^2+$D$6/(1+$B$24)^3+$E$6/(1+$B$24)^4+$F$6/(1+$B$24)^5)+(($F$6*(1+F$23)/($B$24-F$23))/(1+$B$24)^5)-Drivers!$C$36)/Drivers!$C$23 | G24: =(($B$6/(1+$B$24)^1+$C$6/(1+$B$24)^2+$D$6/(1+$B$24)^3+$E$6/(1+$B$24)^4+$F$6/(1+$B$24)^5)+(($F$6*(1+G$23)/($B$24-G$23))/(1+$B$24)^5)-Drivers!$C$36)/Drivers!$C$23
B25: 0.09 | C25: =(($B$6/(1+$B$25)^1+$C$6/(1+$B$25)^2+$D$6/(1+$B$25)^3+$E$6/(1+$B$25)^4+$F$6/(1+$B$25)^5)+(($F$6*(1+C$23)/($B$25-C$23))/(1+$B$25)^5)-Drivers!$C$36)/Drivers!$C$23 | D25: =(($B$6/(1+$B$25)^1+$C$6/(1+$B$25)^2+$D$6/(1+$B$25)^3+$E$6/(1+$B$25)^4+$F$6/(1+$B$25)^5)+(($F$6*(1+D$23)/($B$25-D$23))/(1+$B$25)^5)-Drivers!$C$36)/Drivers!$C$23 | E25: =(($B$6/(1+$B$25)^1+$C$6/(1+$B$25)^2+$D$6/(1+$B$25)^3+$E$6/(1+$B$25)^4+$F$6/(1+$B$25)^5)+(($F$6*(1+E$23)/($B$25-E$23))/(1+$B$25)^5)-Drivers!$C$36)/Drivers!$C$23 | F25: =(($B$6/(1+$B$25)^1+$C$6/(1+$B$25)^2+$D$6/(1+$B$25)^3+$E$6/(1+$B$25)^4+$F$6/(1+$B$25)^5)+(($F$6*(1+F$23)/($B$25-F$23))/(1+$B$25)^5)-Drivers!$C$36)/Drivers!$C$23 | G25: =(($B$6/(1+$B$25)^1+$C$6/(1+$B$25)^2+$D$6/(1+$B$25)^3+$E$6/(1+$B$25)^4+$F$6/(1+$B$25)^5)+(($F$6*(1+G$23)/($B$25-G$23))/(1+$B$25)^5)-Drivers!$C$36)/Drivers!$C$23
B26: 0.095 | C26: =(($B$6/(1+$B$26)^1+$C$6/(1+$B$26)^2+$D$6/(1+$B$26)^3+$E$6/(1+$B$26)^4+$F$6/(1+$B$26)^5)+(($F$6*(1+C$23)/($B$26-C$23))/(1+$B$26)^5)-Drivers!$C$36)/Drivers!$C$23 | D26: =(($B$6/(1+$B$26)^1+$C$6/(1+$B$26)^2+$D$6/(1+$B$26)^3+$E$6/(1+$B$26)^4+$F$6/(1+$B$26)^5)+(($F$6*(1+D$23)/($B$26-D$23))/(1+$B$26)^5)-Drivers!$C$36)/Drivers!$C$23 | E26: =(($B$6/(1+$B$26)^1+$C$6/(1+$B$26)^2+$D$6/(1+$B$26)^3+$E$6/(1+$B$26)^4+$F$6/(1+$B$26)^5)+(($F$6*(1+E$23)/($B$26-E$23))/(1+$B$26)^5)-Drivers!$C$36)/Drivers!$C$23 | F26: =(($B$6/(1+$B$26)^1+$C$6/(1+$B$26)^2+$D$6/(1+$B$26)^3+$E$6/(1+$B$26)^4+$F$6/(1+$B$26)^5)+(($F$6*(1+F$23)/($B$26-F$23))/(1+$B$26)^5)-Drivers!$C$36)/Drivers!$C$23 | G26: =(($B$6/(1+$B$26)^1+$C$6/(1+$B$26)^2+$D$6/(1+$B$26)^3+$E$6/(1+$B$26)^4+$F$6/(1+$B$26)^5)+(($F$6*(1+G$23)/($B$26-G$23))/(1+$B$26)^5)-Drivers!$C$36)/Drivers!$C$23
B27: 0.1 | C27: =(($B$6/(1+$B$27)^1+$C$6/(1+$B$27)^2+$D$6/(1+$B$27)^3+$E$6/(1+$B$27)^4+$F$6/(1+$B$27)^5)+(($F$6*(1+C$23)/($B$27-C$23))/(1+$B$27)^5)-Drivers!$C$36)/Drivers!$C$23 | D27: =(($B$6/(1+$B$27)^1+$C$6/(1+$B$27)^2+$D$6/(1+$B$27)^3+$E$6/(1+$B$27)^4+$F$6/(1+$B$27)^5)+(($F$6*(1+D$23)/($B$27-D$23))/(1+$B$27)^5)-Drivers!$C$36)/Drivers!$C$23 | E27: =(($B$6/(1+$B$27)^1+$C$6/(1+$B$27)^2+$D$6/(1+$B$27)^3+$E$6/(1+$B$27)^4+$F$6/(1+$B$27)^5)+(($F$6*(1+E$23)/($B$27-E$23))/(1+$B$27)^5)-Drivers!$C$36)/Drivers!$C$23 | F27: =(($B$6/(1+$B$27)^1+$C$6/(1+$B$27)^2+$D$6/(1+$B$27)^3+$E$6/(1+$B$27)^4+$F$6/(1+$B$27)^5)+(($F$6*(1+F$23)/($B$27-F$23))/(1+$B$27)^5)-Drivers!$C$36)/Drivers!$C$23 | G27: =(($B$6/(1+$B$27)^1+$C$6/(1+$B$27)^2+$D$6/(1+$B$27)^3+$E$6/(1+$B$27)^4+$F$6/(1+$B$27)^5)+(($F$6*(1+G$23)/($B$27-G$23))/(1+$B$27)^5)-Drivers!$C$36)/Drivers!$C$23
B28: 0.105 | C28: =(($B$6/(1+$B$28)^1+$C$6/(1+$B$28)^2+$D$6/(1+$B$28)^3+$E$6/(1+$B$28)^4+$F$6/(1+$B$28)^5)+(($F$6*(1+C$23)/($B$28-C$23))/(1+$B$28)^5)-Drivers!$C$36)/Drivers!$C$23 | D28: =(($B$6/(1+$B$28)^1+$C$6/(1+$B$28)^2+$D$6/(1+$B$28)^3+$E$6/(1+$B$28)^4+$F$6/(1+$B$28)^5)+(($F$6*(1+D$23)/($B$28-D$23))/(1+$B$28)^5)-Drivers!$C$36)/Drivers!$C$23 | E28: =(($B$6/(1+$B$28)^1+$C$6/(1+$B$28)^2+$D$6/(1+$B$28)^3+$E$6/(1+$B$28)^4+$F$6/(1+$B$28)^5)+(($F$6*(1+E$23)/($B$28-E$23))/(1+$B$28)^5)-Drivers!$C$36)/Drivers!$C$23 | F28: =(($B$6/(1+$B$28)^1+$C$6/(1+$B$28)^2+$D$6/(1+$B$28)^3+$E$6/(1+$B$28)^4+$F$6/(1+$B$28)^5)+(($F$6*(1+F$23)/($B$28-F$23))/(1+$B$28)^5)-Drivers!$C$36)/Drivers!$C$23 | G28: =(($B$6/(1+$B$28)^1+$C$6/(1+$B$28)^2+$D$6/(1+$B$28)^3+$E$6/(1+$B$28)^4+$F$6/(1+$B$28)^5)+(($F$6*(1+G$23)/($B$28-G$23))/(1+$B$28)^5)-Drivers!$C$36)/Drivers!$C$23
A30: Center cell (WACC 9.5% / g 3.5%) = base case; cross-check vs C18 implied per share.

Sheet Notes
A1: MODEL NOTES, METHODOLOGY & CAVEATS
A3: Methodology
A4: Integrated 3-statement model (Income Statement, Balance Sheet, Cash Flow) feeding an unlevered DCF.
A5: Revenue built bottom-up by segment: AI Semiconductor, Non-AI Semiconductor, Infrastructure Software.
A6: Every projection is a live formula off the Drivers tab — change an assumption and the model + DCF + sensitivity reflow.
A7: DCF discounts unlevered FCF at a computed WACC; terminal value via Gordon growth. EV less net debt = equity value.
A9: Base-case stance (IMPORTANT)
A10: BASE case HAIRCUTS management's 'line of sight to $100B+ AI revenue in 2027' to ~$76B (-24%) for execution and
A11: OpenAI-financing risk (The Information, May 2026: $18B first-phase funding gap; Microsoft-40% structure rejected).
A12: Result: base-case intrinsic value lands well BELOW the ~$460 market price — i.e., the stock is pricing the BULL AI ramp.
A13: This is the central valuation finding. See the bull/base/bear framing in the deck; sensitivity table shows the WACC/g swing.
A15: Data sources
... A31: 4. Research / decision-framing only — NOT investment advice. Cross-check against a primary terminal before acting.
