Workbook

Sheet Inputs
A1: AI SEMICONDUCTORS & INFRASTRUCTURE SOFTWARE — COMPARABLE COMPANY ANALYSIS
A2: Broadcom (AVGO) • NVIDIA (NVDA) • AMD (AMD) • Marvell Technology (MRVL) • Qualcomm (QCOM) • Texas Instruments (TXN) • Oracle (ORCL)
A3: As of ~June 1, 2026 | $ in millions except ratios | Stats computed over the 5 semis peers (NVDA, AMD, MRVL, QCOM, TXN); AVGO = target, ORCL = software anchor (memo)
A5: RAW INPUTS — cell comments cite source / assumption
A6: Company | B6: Ticker | C6: Mkt Cap | D6: Net Debt | E6: Revenue (TTM) | F6: Rev Growth % | G6: Gross Margin % | H6: EBITDA (TTM) | I6: Net Income (TTM) | J6: Fwd P/E | K6: Notes
A7: Broadcom | B7: AVGO | C7: 2175800 | D7: 51857 | E7: 68300 | F7: 0.29 | G7: 0.68 | H7: 40500 | I7: 25000 | J7: 31 | K7: TARGET
A8: NVIDIA | B8: NVDA | C8: 5460000 | D8: -4700 | E8: 253500 | F8: 0.85 | G8: 0.749 | H8: 174400 | I8: 159600 | J8: 26
A9: AMD | B9: AMD | C9: 839000 | D9: -9100 | E9: 37450 | F9: 0.38 | G9: 0.53 | H9: 8090 | I9: 5000 | J9: 33
A10: Marvell Technology | B10: MRVL | C10: 192000 | D10: 1430 | E10: 8600 | F10: 0.28 | G10: 0.521 | H10: 3000 | I10: 300 | J10: 48
A11: Qualcomm | B11: QCOM | C11: 215000 | D11: 5500 | E11: 44490 | F11: -0.03 | G11: 0.54 | H11: 13956 | I11: 9900 | J11: 14
A12: Texas Instruments | B12: TXN | C12: 287000 | D12: 8000 | E12: 18440 | F12: 0.19 | G12: 0.58 | H12: 8821 | I12: 5370 | J12: 30
A13: Oracle | B13: ORCL | C13: 640000 | D13: 96000 | E13: 64080 | F13: 0.22 | G13: 0.7 | H13: 30618 | I13: 16200 | J13: 28 | K13: SOFTWARE ANCHOR (memo)

Sheet Operating Metrics
A1: OPERATING STATISTICS & FINANCIAL METRICS
A2: Formulas reference Inputs tab. Stats over the 5 semis peers only.
A6: Company | B6: Revenue (TTM) | C6: Rev Growth (YoY) | D6: Gross Margin | E6: EBITDA (TTM) | F6: EBITDA Margin
A7: Broadcom | B7: =Inputs!E7 | C7: =Inputs!F7 | D7: =Inputs!G7 | E7: =Inputs!H7 | F7: =Inputs!H7/Inputs!E7
A8: NVIDIA | B8: =Inputs!E8 | C8: =Inputs!F8 | D8: =Inputs!G8 | E8: =Inputs!H8 | F8: =Inputs!H8/Inputs!E8
A9: AMD | B9: =Inputs!E9 | C9: =Inputs!F9 | D9: =Inputs!G9 | E9: =Inputs!H9 | F9: =Inputs!H9/Inputs!E9
A10: Marvell Technology | B10: =Inputs!E10 | C10: =Inputs!F10 | D10: =Inputs!G10 | E10: =Inputs!H10 | F10: =Inputs!H10/Inputs!E10
A11: Qualcomm | B11: =Inputs!E11 | C11: =Inputs!F11 | D11: =Inputs!G11 | E11: =Inputs!H11 | F11: =Inputs!H11/Inputs!E11
A12: Texas Instruments | B12: =Inputs!E12 | C12: =Inputs!F12 | D12: =Inputs!G12 | E12: =Inputs!H12 | F12: =Inputs!H12/Inputs!E12
A13: Oracle | B13: =Inputs!E13 | C13: =Inputs!F13 | D13: =Inputs!G13 | E13: =Inputs!H13 | F13: =Inputs!H13/Inputs!E13
A14: Maximum | C14: =MAX(C8:C12) | D14: =MAX(D8:D12) | F14: =MAX(F8:F12)
A15: 75th Percentile | C15: =QUARTILE(C8:C12,3) | D15: =QUARTILE(D8:D12,3) | F15: =QUARTILE(F8:F12,3)
A16: Median | C16: =MEDIAN(C8:C12) | D16: =MEDIAN(D8:D12) | F16: =MEDIAN(F8:F12)
A17: 25th Percentile | C17: =QUARTILE(C8:C12,1) | D17: =QUARTILE(D8:D12,1) | F17: =QUARTILE(F8:F12,1)
A18: Minimum | C18: =MIN(C8:C12) | D18: =MIN(D8:D12) | F18: =MIN(F8:F12)

Sheet Valuation
A1: VALUATION MULTIPLES
A2: EV = Mkt Cap + Net Debt. NM where denominator <= 0. Forward P/E is the cleaner cross-peer gauge (GAAP earnings distorted by amortization at AMD/MRVL).
A6: Company | B6: Mkt Cap | C6: EV | D6: EV / Rev | E6: EV / EBITDA | F6: P/E (TTM) | G6: Fwd P/E | H6: Comment
A7: Broadcom | B7: =Inputs!C7 | C7: =Inputs!C7+Inputs!D7 | D7: =(Inputs!C7+Inputs!D7)/Inputs!E7 | E7: =IF(Inputs!H7>0,(Inputs!C7+Inputs!D7)/Inputs!H7,"NM") | F7: =IF(Inputs!I7>0,Inputs!C7/Inputs!I7,"NM") | G7: =Inputs!J7 | H7: Target. TTM P/E optically high (~87x) on GAAP NI; fwd ~31x. DCF base ~$246 << $460 mkt (see model).
A8: NVIDIA | B8: =Inputs!C8 | C8: =Inputs!C8+Inputs!D8 | D8: =(Inputs!C8+Inputs!D8)/Inputs!E8 | E8: =IF(Inputs!H8>0,(Inputs!C8+Inputs!D8)/Inputs!H8,"NM") | F8: =IF(Inputs!I8>0,Inputs!C8/Inputs!I8,"NM") | G8: =Inputs!J8 | H8: Cheapest large-cap on earnings (P/E ~34) despite $5.5T cap — vast profitability; net cash.
A9: AMD | B9: =Inputs!C9 | C9: =Inputs!C9+Inputs!D9 | D9: =(Inputs!C9+Inputs!D9)/Inputs!E9 | E9: =IF(Inputs!H9>0,(Inputs!C9+Inputs!D9)/Inputs!H9,"NM") | F9: =IF(Inputs!I9>0,Inputs!C9/Inputs!I9,"NM") | G9: =Inputs!J9 | H9: Extreme TTM multiples (GAAP ramping); read on EV/Rev (~22x) and fwd P/E.
A10: Marvell Technology | B10: =Inputs!C10 | C10: =Inputs!C10+Inputs!D10 | D10: =(Inputs!C10+Inputs!D10)/Inputs!E10 | E10: =IF(Inputs!H10>0,(Inputs!C10+Inputs!D10)/Inputs!H10,"NM") | F10: =IF(Inputs!I10>0,Inputs!C10/Inputs!I10,"NM") | G10: =Inputs!J10 | H10: Purest custom-silicon comp; GAAP P/E NM-high (amortization); fwd ~48x. Re-rated on NVDA endorsement.
A11: Qualcomm | B11: =Inputs!C11 | C11: =Inputs!C11+Inputs!D11 | D11: =(Inputs!C11+Inputs!D11)/Inputs!E11 | E11: =IF(Inputs!H11>0,(Inputs!C11+Inputs!D11)/Inputs!H11,"NM") | F11: =IF(Inputs!I11>0,Inputs!C11/Inputs!I11,"NM") | G11: =Inputs!J11 | H11: Mature-semi value name; cheapest fwd P/E (~14x). Limited AI-accelerator exposure.
A12: Texas Instruments | B12: =Inputs!C12 | C12: =Inputs!C12+Inputs!D12 | D12: =(Inputs!C12+Inputs!D12)/Inputs!E12 | E12: =IF(Inputs!H12>0,(Inputs!C12+Inputs!D12)/Inputs!H12,"NM") | F12: =IF(Inputs!I12>0,Inputs!C12/Inputs!I12,"NM") | G12: =Inputs!J12 | H12: Analog; high multiples reflect trough earnings in heavy-capex cycle, not just quality.
A13: Oracle | B13: =Inputs!C13 | C13: =Inputs!C13+Inputs!D13 | D13: =(Inputs!C13+Inputs!D13)/Inputs!E13 | E13: =IF(Inputs!H13>0,(Inputs!C13+Inputs!D13)/Inputs!H13,"NM") | F13: =IF(Inputs!I13>0,Inputs!C13/Inputs!I13,"NM") | G13: =Inputs!J13 | H13: Software anchor (memo). Now an AI-capex story; ~$96B net debt rising; EV/Rev ~12x embeds high growth.
A14: Maximum | D14: =MAX(D8:D12) | E14: =MAX(E8:E12) | F14: =MAX(F8:F12) | G14: =MAX(G8:G12)
A15: 75th Percentile | D15: =QUARTILE(D8:D12,3) | E15: =QUARTILE(E8:E12,3) | F15: =QUARTILE(F8:F12,3) | G15: =QUARTILE(G8:G12,3)
A16: Median | D16: =MEDIAN(D8:D12) | E16: =MEDIAN(E8:E12) | F16: =MEDIAN(F8:F12) | G16: =MEDIAN(G8:G12)
A17: 25th Percentile | D17: =QUARTILE(D8:D12,1) | E17: =QUARTILE(E8:E12,1) | F17: =QUARTILE(F8:F12,1) | G17: =QUARTILE(G8:G12,1)
A18: Minimum | D18: =MIN(D8:D12) | E18: =MIN(E8:E12) | F18: =MIN(F8:F12) | G18: =MIN(G8:G12)

Sheet Growth & AI Exposure
A1: GROWTH & AI EXPOSURE — Industry-Specific Lens
A2: For this peer set the differentiators are AI revenue exposure, growth, and PEG (growth-adjusted valuation). AI revenue figures are [E] where not separately disclosed.
A6: Company | B6: Rev Growth (YoY) | C6: Fwd P/E | D6: PEG (fwd P/E ÷ growth) | E6: AI exposure | F6: Posture
A7: Broadcom | B7: =Inputs!F7 | C7: =Inputs!J7 | D7: =IF(Inputs!F7>0,Inputs!J7/(Inputs!F7*100),"NM") | E7: High — direct | F7: Custom XPU/ASIC + AI networking; 6 committed hyperscaler customers; $73B AI backlog
A8: NVIDIA | B8: =Inputs!F8 | C8: =Inputs!J8 | D8: =IF(Inputs!F8>0,Inputs!J8/(Inputs!F8*100),"NM") | E8: Very high — merchant GPU leader | F8: ~70%+ of AI accelerator market; the comp everyone anchors to
A9: AMD | B9: =Inputs!F9 | C9: =Inputs!J9 | D9: =IF(Inputs!F9>0,Inputs!J9/(Inputs!F9*100),"NM") | E9: High — #2 merchant GPU | F9: MI-series data-center GPUs; ~10-15% accelerator share
A10: Marvell Technology | B10: =Inputs!F10 | C10: =Inputs!J10 | D10: =IF(Inputs!F10>0,Inputs!J10/(Inputs!F10*100),"NM") | E10: High — custom silicon | F10: Closest AVGO ASIC comp; Amazon Trainium, Microsoft Maia; ~76% DC revenue
A11: Qualcomm | B11: =Inputs!F11 | C11: =Inputs!J11 | D11: =IF(Inputs!F11>0,Inputs!J11/(Inputs!F11*100),"NM") | E11: Low — edge/on-device | F11: Handset/auto/IoT; limited data-center AI accelerator exposure
A12: Texas Instruments | B12: =Inputs!F12 | C12: =Inputs!J12 | D12: =IF(Inputs!F12>0,Inputs!J12/(Inputs!F12*100),"NM") | E12: Low — analog content | F12: Benefits from AI server analog content, but no accelerator franchise
A13: Oracle | B13: =Inputs!F13 | C13: =Inputs!J13 | D13: =IF(Inputs!F13>0,Inputs!J13/(Inputs!F13*100),"NM") | E13: High — AI infra demand | F13: OCI capacity for AI training (incl. OpenAI); software anchor for VMware
A14: Maximum | B14: =MAX(B8:B12) | C14: =MAX(C8:C12) | D14: =MAX(D8:D12)
A15: 75th Percentile | B15: =QUARTILE(B8:B12,3) | C15: =QUARTILE(C8:C12,3) | D15: =QUARTILE(D8:D12,3)
A16: Median | B16: =MEDIAN(B8:B12) | C16: =MEDIAN(C8:C12) | D16: =MEDIAN(D8:D12)
A17: 25th Percentile | B17: =QUARTILE(B8:B12,1) | C17: =QUARTILE(C8:C12,1) | D17: =QUARTILE(D8:D12,1)
A18: Minimum | B18: =MIN(B8:B12) | C18: =MIN(C8:C12) | D18: =MIN(D8:D12)

Sheet Notes
A1: NOTES, METHODOLOGY & DATA-SOURCE CAVEATS
A3: Peer framing
A4: Second framing (user-selected): semiconductor cohort + one infrastructure-software anchor.
A5: Stat block (Max/75th/Median/25th/Min) is computed over the 5 SEMIS peers only: NVDA, AMD, MRVL, QCOM, TXN.
A6: AVGO is the target (compare to the semis median). ORCL is a software-anchor MEMO row for the VMware (~40%) segment — excluded from semis stats.
A7: Rationale: you don't median a software multiple into a semis set; ORCL frames the software side qualitatively + on its own multiples.
A9: Data sources
A10: Reported figures: company IR releases and SEC 10-Q/10-K filings for each issuer (most recent quarter as of May/June 2026).
A11: Market data (caps, EV): StockAnalysis.com / companiesmarketcap / GuruFocus, ~June 1-2, 2026.
A12: MCP terminal connectors (CapIQ/FactSet/Daloopa) were NOT configured; public sources used and flagged [E] where estimated.
A14: Key adjustments & caveats
A15: GAAP TTM P/E is distorted for AMD and MRVL (earnings depressed by acquired-intangible amortization) — use FORWARD P/E for comparability.
... A25: Build script: build_comps.py — re-run after updating INPUTS.
